Workbook
Name IQ_CH: 110000
Name IQ_CQ: 5000
Name IQ_CY: 10000
Name IQ_DAILY: 500000
Name IQ_FH: 100000
Name IQ_FQ: 500
Name IQ_FY: 1000
Name IQ_LTM: 2000
Name IQ_MONTH: 15000
Name IQ_NTM: 6000
Name IQ_WEEK: 50000
Name IQ_YTD: 3000
Name UPDATE: 'Data Sheet'!$E$1

Sheet Data>

Sheet Data Room>

Sheet Football Field Analysis
L4: Fooball Field Analysis - Data
N5: Open Low | O5: Low | P5: Open High | Q5: High
L6: Relative Valuation | N6: 1393.8 | O6: =N6 -> 1393.8 | P6: 1797.1 | Q6: =P6 -> 1797.1
L7: DCF Bear | N7: ='DCF>'!J17 -> 468.20006 | O7: =N7 -> 468.20006 | P7: ='DCF>'!J22 -> 665.9116 | Q7: =P7 -> 665.9116
L8: DCF Base | N8: ='DCF>'!H17 -> 514.97547 | O8: =N8 -> 514.97547 | P8: ='DCF>'!H22 -> 791.08837 | Q8: =P8 -> 791.08837
L9: DCF Bull | N9: ='DCF>'!G17 -> 545.08788 | O9: =N9 -> 545.08788 | P9: 883.4 | Q9: =P9 -> 883.4
L10: 52 Weeks Range | N10: 2115 | O10: =N10 -> 2115 | P10: 2985.7 | Q10: =P10 -> 2985.7

Sheet VAR
B1: 5 Year -Daily
B3: Date | C3: Price | D3: Returns | E3: Shorted Returns | G3: Replication | H3: Simulated Returns | J3: calculation of value at Risk -Asian Paints (Historical)
B4: 43910 | C4: 1741.2 | D4: =(C4-C5)/C5 -> -0.37399558 | E4: 0.094096579 | G4: 1 | H4: =_xlfn.NORM.INV(RAND(),N$6,N$7) -> -0.015343303
B5: 44330 | C5: 2781.45 | D5: =(C5-C6)/C6 -> 0.65779592 | E5: 0.086503906 | G5: 2 | H5: =_xlfn.NORM.INV(RAND(),N$6,N$7) -> 0.0075337319 | J5: Historical Approach
B6: 43728 | C6: 1677.8 | D6: =(C6-C7)/C7 -> 0.024204133 | E6: 0.080221478 | G6: 3 | H6: =_xlfn.NORM.INV(RAND(),N$6,N$7) -> -0.0064417568 | J6: Mean | N6: =AVERAGE(E4:E2746) -> 0.00058458404
B7: 43928 | C7: 1638.15 | D7: =(C7-C8)/C8 -> -0.089208273 | E7: 0.075501428 | G7: 4 | H7: =_xlfn.NORM.INV(RAND(),N$6,N$7) -> -0.00020652813 | J7: Std | N7: =_xlfn.STDEV.S(E4:E2746) -> 0.015235186
B8: 43731 | C8: 1798.6 | D8: =(C8-C9)/C9 -> 0.39534523 | E8: 0.071999046 | G8: 5 | H8: =_xlfn.NORM.INV(RAND(),N$6,N$7) -> 0.0041436042 | J8: Min | N8: =MIN(E4:E2746) -> -0.14323455
B9: 43231 | C9: 1289 | D9: =(C9-C10)/C10 -> -0.3101049 | E9: 0.062391824 | G9: 6 | H9: =_xlfn.NORM.INV(RAND(),N$6,N$7) -> 0.014883259 | J9: Max | N9: =MAX(E4:E2746) -> 0.094096579
B10: 43864 | C10: 1868.4 | D10: =(C10-C11)/C11 -> -0.41030173 | E10: 0.060686915 | G10: 7 | H10: =_xlfn.NORM.INV(RAND(),N$6,N$7) -> -0.0098921144 | J10: current Price | N10: ='Data Sheet'!B8 -> 2605.6
B11: 44397 | C11: 3168.4 | D11: =(C11-C12)/C12 -> 1.8116071 | E11: 0.060481307 | G11: 8 | H11: =_xlfn.NORM.INV(RAND(),N$6,N$7) -> -0.021209391
B12: 42579 | C12: 1126.9 | D12: =(C12-C13)/C13 -> -0.60840935 | E12: 0.059315661 | G12: 9 | H12: =_xlfn.NORM.INV(RAND(),N$6,N$7) -> -0.005164497 | J12: Percentile | K12: Confidence | L12: VAR% | M12: Stock Price | N12: VAR(INR)
B13: 44629 | C13: 2877.75 | D13: =(C13-C14)/C14 -> 0.31320161 | E13: 0.053850661 | G13: 10 | H13: =_xlfn.NORM.INV(RAND(),N$6,N$7) -> -0.0037913592 | J13: 0.05 | K13: =100%-J13 -> 0.95 | L13: =_xlfn.PERCENTILE.INC($E$4:$E$2746,J13) -> -0.022436073 | M13: =$N$10*(1-L13) -> 2664.0594 | N13: =$N$10-M13 -> -58.459431
B14: 44131 | C14: 2191.4 | D14: =(C14-C15)/C15 -> 1.6554377 | E14: 0.053000817 | G14: 11 | H14: =_xlfn.NORM.INV(RAND(),N$6,N$7) -> 0.0027877019 | J14: 0.01 | K14: =100%-J14 -> 0.99 | L14: =_xlfn.PERCENTILE.INC($E$4:$E$2746,J14) -> -0.040442255 | M14: =$N$10*(1-L14) -> 2710.9763 | N14: =$N$10-M14 -> -105.37634
B15: 42192 | C15: 825.25 | D15: =(C15-C16)/C16 -> -0.67248735 | E15: 0.050872278 | G15: 12 | H15: =_xlfn.NORM.INV(RAND(),N$6,N$7) -> -0.0097790102 | J15: 0.005 | K15: =100%-J15 -> 0.995 | L15: =_xlfn.PERCENTILE.INC($E$4:$E$2746,J15) -> -0.047449989 | M15: =$N$10*(1-L15) -> 2729.2357 | N15: =$N$10-M15 -> -123.63569
B16: 44281 | C16: 2519.75 | D16: =(C16-C17)/C17 -> 0.60708591 | E16: 0.04893431 | G16: 13 | H16: =_xlfn.NORM.INV(RAND(),N$6,N$7) -> -0.00037883057
B17: 43972 | C17: 1567.9 | D17: =(C17-C18)/C18 -> -0.13330201 | E17: 0.048096527 | G17: 14 | H17: =_xlfn.NORM.INV(RAND(),N$6,N$7) -> 0.021599908 | J17: Monte Carlo Simulation
B18: 43943 | C18: 1809.05 | D18: =(C18-C19)/C19 -> 0.48197755 | E18: 0.048056312 | G18: 15 | H18: =_xlfn.NORM.INV(RAND(),N$6,N$7) -> 0.0011472728 | J18: Mean | N18: =AVERAGE(H4:H5003) -> 0.00054713942
B19: 42979 | C19: 1220.7 | D19: =(C19-C20)/C20 -> 0.30479397 | E19: 0.047002316 | G19: 16 | H19: =_xlfn.NORM.INV(RAND(),N$6,N$7) -> 0.0085524519 | J19: Std | N19: =_xlfn.STDEV.S(H4:H5003) -> 0.015056564
B20: 42690 | C20: 935.55 | D20: =(C20-C21)/C21 -> -0.48263562 | E20: 0.046593579 | G20: 17 | H20: =_xlfn.NORM.INV(RAND(),N$6,N$7) -> -0.015238203 | J20: Min | N20: =MIN(H4:H5003) -> -0.048836929
B21: 44050 | C21: 1808.3 | D21: =(C21-C22)/C22 -> -0.18383282 | E21: 0.045199699 | G21: 18 | H21: =_xlfn.NORM.INV(RAND(),N$6,N$7) -> 0.0027088428 | J21: Max | N21: =MAX(H4:H5003) -> 0.05013335
B22: 46105 | C22: 2215.6 | D22: =(C22-C23)/C23 -> 0.13112955 | E22: 0.04509434 | G22: 19 | H22: =_xlfn.NORM.INV(RAND(),N$6,N$7) -> 0.0060332725 | J22: current Price | N22: =N10 -> 2605.6
B23: 44064 | C23: 1958.75 | D23: =(C23-C24)/C24 -> -0.32285275 | E23: 0.044805974 | G23: 20 | H23: =_xlfn.NORM.INV(RAND(),N$6,N$7) -> 0.0056684664
B24: 45425 | C24: 2892.65 | D24: =(C24-C25)/C25 -> 0.17009486 | E24: 0.044711703 | G24: 21 | H24: =_xlfn.NORM.INV(RAND(),N$6,N$7) -> -0.036661075 | J24: Percentile | K24: Confidence | L24: VAR% | M24: Stock Price | N24: VAR(INR)
B25: 44271 | C25: 2472.15 | D25: =(C25-C26)/C26 -> 0.08809419 | E25: 0.044688134 | G25: 22 | H25: =_xlfn.NORM.INV(RAND(),N$6,N$7) -> 9.729192e-05 | J25: 0.05 | K25: =100%-J25 -> 0.95 | L25: =_xlfn.PERCENTILE.INC($H$4:$H$5003,J25) -> -0.023964871 | M25: =$N$10*(1-L25) -> 2668.0429 | N25: =$N$10-M25 -> -62.442869
B26: 45722 | C26: 2272 | D26: =(C26-C27)/C27 -> -0.0092015176 | E26: 0.043709948 | G26: 23 | H26: =_xlfn.NORM.INV(RAND(),N$6,N$7) -> -0.008857614 | J26: 0.01 | K26: =100%-J26 -> 0.99 | L26: =_xlfn.PERCENTILE.INC($H$4:$H$5003,J26) -> -0.035289848 | M26: =$N$10*(1-L26) -> 2697.5512 | N26: =$N$10-M26 -> -91.951227
B27: 46120 | C27: 2293.1 | D27: =(C27-C28)/C28 -> 0.87283567 | E27: 0.043314073 | G27: 24 | H27: =_xlfn.NORM.INV(RAND(),N$6,N$7) -> -0.0019621521 | J27: 0.005 | K27: =100%-J27 -> 0.995 | L27: =_xlfn.PERCENTILE.INC($H$4:$H$5003,J27) -> -0.037907189 | M27: =$N$10*(1-L27) -> 2704.371 | N27: =$N$10-M27 -> -98.770971
B28: 43032 | C28: 1224.4 | D28: =(C28-C29)/C29 -> -0.2671116 | E28: 0.043241171 | G28: 25 | H28: =_xlfn.NORM.INV(RAND(),N$6,N$7) -> 0.010044363
B29: 43921 | C29: 1670.65 | D29: =(C29-C30)/C30 -> -0.3627365 | E29: 0.042689967 | G29: 26 | H29: =_xlfn.NORM.INV(RAND(),N$6,N$7) -> 0.011937102
B30: 46155 | C30: 2621.6 | D30: =(C30-C31)/C31 -> 0.0081913625 | E30: 0.042510041 | G30: 27 | H30: =_xlfn.NORM.INV(RAND(),N$6,N$7) -> -0.023890221
B31: 45967 | C31: 2600.3 | D31: =(C31-C32)/C32 -> 1.1897263 | E31: 0.042413309 | G31: 28 | H31: =_xlfn.NORM.INV(RAND(),N$6,N$7) -> 0.0037895656
B32: 43397 | C32: 1187.5 | D32: =(C32-C33)/C33 -> -0.57120676 | E32: 0.042215201 | G32: 29 | H32: =_xlfn.NORM.INV(RAND(),N$6,N$7) -> 0.010184258
B33: 45973 | C33: 2769.4 | D33: =(C33-C34)/C34 -> 0.16916452 | E33: 0.041911211 | G33: 30 | H33: =_xlfn.NORM.INV(RAND(),N$6,N$7) -> 0.010159629
B34: 46122 | C34: 2368.7 | D34: =(C34-C35)/C35 -> -0.27582623 | E34: 0.041232582 | G34: 31 | H34: =_xlfn.NORM.INV(RAND(),N$6,N$7) -> 0.0098234173
B35: 44607 | C35: 3270.9 | D35: =(C35-C36)/C36 -> 2.7424485 | E35: 0.041024825 | G35: 32 | H35: =_xlfn.NORM.INV(RAND(),N$6,N$7) -> -0.0045960363
B36: 42345 | C36: 874 | D36: =(C36-C37)/C37 -> -0.66627847 | E36: 0.04047619 | G36: 33 | H36: =_xlfn.NORM.INV(RAND(),N$6,N$7) -> -0.0043629458
B37: 44292 | C37: 2618.95 | D37: =(C37-C38)/C38 -> 0.041580496 | E37: 0.039967438 | G37: 34 | H37: =_xlfn.NORM.INV(RAND(),N$6,N$7) -> -0.020107756
B38: 45947 | C38: 2514.4 | D38: =(C38-C39)/C39 -> 0.26727483 | E38: 0.039910666 | G38: 35 | H38: =_xlfn.NORM.INV(RAND(),N$6,N$7) -> 0.023987967
B39: 44075 | C39: 1984.1 | D39: =(C39-C40)/C40 -> 0.13403064 | E39: 0.039122237 | G39: 36 | H39: =_xlfn.NORM.INV(RAND(),N$6,N$7) -> 0.022736055
... B2746: 43913 | C2746: 1491.8 | D2746: =(C2746-C2747)/C2747 -> 0.97236729 | E2746: -0.14323455 | G2746: 2743 | H2746: =_xlfn.NORM.INV(RAND(),N$6,N$7) -> 0.012361601
B2747: 42157 | C2747: 756.35 | G2747: 2744 | H2747: =_xlfn.NORM.INV(RAND(),N$6,N$7) -> -0.0092708701
G2748: 2745 | H2748: =_xlfn.NORM.INV(RAND(),N$6,N$7) -> 0.018075537
G2749: 2746 | H2749: =_xlfn.NORM.INV(RAND(),N$6,N$7) -> 0.011479809
G2750: 2747 | H2750: =_xlfn.NORM.INV(RAND(),N$6,N$7) -> 0.00074302867
G2751: 2748 | H2751: =_xlfn.NORM.INV(RAND(),N$6,N$7) -> -2.5853079e-05
G2752: 2749 | H2752: =_xlfn.NORM.INV(RAND(),N$6,N$7) -> -0.0013316281
G2753: 2750 | H2753: =_xlfn.NORM.INV(RAND(),N$6,N$7) -> -0.0094307252
G2754: 2751 | H2754: =_xlfn.NORM.INV(RAND(),N$6,N$7) -> 0.020676174
G2755: 2752 | H2755: =_xlfn.NORM.INV(RAND(),N$6,N$7) -> -0.013502201
G2756: 2753 | H2756: =_xlfn.NORM.INV(RAND(),N$6,N$7) -> -0.0049553002
G2757: 2754 | H2757: =_xlfn.NORM.INV(RAND(),N$6,N$7) -> -0.019303822
G2758: 2755 | H2758: =_xlfn.NORM.INV(RAND(),N$6,N$7) -> 0.024302838
G2759: 2756 | H2759: =_xlfn.NORM.INV(RAND(),N$6,N$7) -> 0.015267283
... G5003: 5000 | H5003: =_xlfn.NORM.INV(RAND(),N$6,N$7) -> 0.0024317666

Sheet Altman Z Score
B3: ='Data Sheet'!B1 -> ASIAN PAINTS LTD
B4: =CONCATENATE("(",_xlfn.XLOOKUP(B3,'List Of Stocks'!B2:B5442,'List Of Stocks'!D2:D5442), " | ","BSE Code: ",_xlfn.XLOOKUP('Altman Z Score'!B3,'List Of Stocks'!B2:B5442,'List Of Stocks'!C2:C5442,,0)," ) ") -> (ASIANPAINT | BSE Code: 500820 )
B5: =CONCATENATE("INR", " ",'Data Sheet'!B8) -> INR 2605.6
B6: ="52 Week" & " "&"("&"High -" & " INR " &'Football Field Analysis'!Q10 & " " &"LOW - " & " INR " &'Football Field Analysis'!N10 &")" -> 52 Week (High - INR 2985.7 LOW - INR 2115)
B8: Altman's Z Score Analysis
B9: Asian Paints Ltd is an Indian multinational paint company, headquartered in Mumbai.The company is engaged in the business of manufacturing, selling and distribution of paints, coatings, products related to home décor, bath fittings and providing related services. Asian Paints is India's largest paints company by market share.The company has 27 paint manufacturing facilities in 15 countries, servicing consumers in over 60 countries. Asian Paints is also present in the home improvement and décor space in India
B16: Financial Summary
B67: Working Capital/Total Assets
C68: =HistoricalFS!F3 -> 43555 | D68: =HistoricalFS!G3 -> 43921 | E68: =HistoricalFS!H3 -> 44286 | F68: =HistoricalFS!I3 -> 44651 | G68: =HistoricalFS!J3 -> 45016 | H68: =HistoricalFS!K3 -> 45382 | I68: =HistoricalFS!L3 -> 45747
B69: Working Capital | C69: ='Data Sheet'!E65-'Data Sheet'!E60 -> 1515.34 | D69: ='Data Sheet'!F65-'Data Sheet'!F60 -> 2817.26 | E69: ='Data Sheet'!G65-'Data Sheet'!G60 -> 3121.11 | F69: ='Data Sheet'!H65-'Data Sheet'!H60 -> 6205.42 | G69: ='Data Sheet'!I65-'Data Sheet'!I60 -> 6873.09 | H69: ='Data Sheet'!J65-'Data Sheet'!J60 -> 6769.77 | I69: ='Data Sheet'!K65-'Data Sheet'!K60 -> 6490.76
B70: Total Assets | C70: ='Data Sheet'!E66 -> 16248.84 | D70: ='Data Sheet'!F66 -> 16137.97 | E70: ='Data Sheet'!G66 -> 20355.34 | F70: ='Data Sheet'!H66 -> 22958.43 | G70: ='Data Sheet'!I66 -> 25779.33 | H70: ='Data Sheet'!J66 -> 29900.77 | I70: ='Data Sheet'!K66 -> 30355.25
B71: Working Capital/Total Assets(A) | C71: =C69/C70 -> 0.09325835 | D71: =D69/D70 -> 0.17457338 | E71: =E69/E70 -> 0.15333126 | F71: =F69/F70 -> 0.27028939 | G71: =G69/G70 -> 0.26661244 | H71: =H69/H70 -> 0.22640788 | I71: =I69/I70 -> 0.2138266
B73: Retained Earnings/Total Assets
C74: =C68 -> 43555 | D74: =D68 -> 43921 | E74: =E68 -> 44286 | F74: =F68 -> 44651 | G74: =G68 -> 45016 | H74: =H68 -> 45382 | I74: =I68 -> 45747
B75: Retained Earnings | C75: =HistoricalFS!F36*HistoricalFS!F38*HistoricalFS!F44 -> 927.11 | D75: =HistoricalFS!G36*HistoricalFS!G38*HistoricalFS!G44 -> 1273.05 | E75: =HistoricalFS!H36*HistoricalFS!H38*HistoricalFS!H44 -> 1162.93 | F75: =HistoricalFS!I36*HistoricalFS!I38*HistoricalFS!I44 -> 952.06 | G75: =HistoricalFS!J36*HistoricalFS!J38*HistoricalFS!J44 -> 1303.52 | H75: =HistoricalFS!K36*HistoricalFS!K38*HistoricalFS!K44 -> 1542.59 | I75: =HistoricalFS!L36*HistoricalFS!L38*HistoricalFS!L44 -> 980.67
B76: =B70 -> Total Assets | C76: =C$70 -> 16248.84 | D76: =D$70 -> 16137.97 | E76: =E$70 -> 20355.34 | F76: =F$70 -> 22958.43 | G76: =G$70 -> 25779.33 | H76: =H$70 -> 29900.77 | I76: =I$70 -> 30355.25
B77: Retained Earnings/Total Assets(B) | C77: =C75/C76 -> 0.057056996 | D77: =D75/D76 -> 0.078885386 | E77: =E75/E76 -> 0.057131446 | F77: =F75/F76 -> 0.041468864 | G77: =G75/G76 -> 0.050564541 | H77: =H75/H76 -> 0.05159031 | I77: =I75/I76 -> 0.032306438
B79: EBIT/Total Assets
C80: =C74 -> 43555 | D80: =D74 -> 43921 | E80: =E74 -> 44286 | F80: =F74 -> 44651 | G80: =G74 -> 45016 | H80: =H74 -> 45382 | I80: =I74 -> 45747
B81: EBIT | C81: =HistoricalFS!F18-HistoricalFS!F24 -> 3142.8 | D81: =HistoricalFS!G18-HistoricalFS!G24 -> 3381.27 | E81: =HistoricalFS!H18-HistoricalFS!H24 -> 4064.33 | F81: =HistoricalFS!I18-HistoricalFS!I24 -> 3987.25 | G81: =HistoricalFS!J18-HistoricalFS!J24 -> 5401.82 | H81: =HistoricalFS!K18-HistoricalFS!K24 -> 6731.98 | I81: =HistoricalFS!L18-HistoricalFS!L24 -> 4979.87
B82: =B76 -> Total Assets | C82: =C76 -> 16248.84 | D82: =D76 -> 16137.97 | E82: =E76 -> 20355.34 | F82: =F76 -> 22958.43 | G82: =G76 -> 25779.33 | H82: =H76 -> 29900.77 | I82: =I76 -> 30355.25
B83: EBIT/Total Assets(C) | C83: =C81/C82 -> 0.19341688 | D83: =D81/D82 -> 0.20952264 | E83: =E81/E82 -> 0.19966898 | F83: =F81/F82 -> 0.17367259 | G83: =G81/G82 -> 0.20954074 | H83: =H81/H82 -> 0.22514403 | I83: =I81/I82 -> 0.16405301
B85: Market cap/Long Term Liabilities
C86: =C80 -> 43555 | D86: =D80 -> 43921 | E86: =E80 -> 44286 | F86: =F80 -> 44651 | G86: =G80 -> 45016 | H86: =H80 -> 45382 | I86: =I80 -> 45747
B87: Market Cap | C87: =('Data Sheet'!E70*'Data Sheet'!E90)/10000000 -> 143179.45 | D87: =('Data Sheet'!F70*'Data Sheet'!F90)/10000000 -> 159850.31 | E87: =('Data Sheet'!G70*'Data Sheet'!G90)/10000000 -> 243386.85 | F87: =('Data Sheet'!H70*'Data Sheet'!H90)/10000000 -> 295428.12 | G87: =('Data Sheet'!I70*'Data Sheet'!I90)/10000000 -> 264896.86 | H87: =('Data Sheet'!J70*'Data Sheet'!J90)/10000000 -> 273059.63 | I87: =('Data Sheet'!K70*'Data Sheet'!K90)/10000000 -> 224514.63
B88: Long Term Liability | C88: ='Data Sheet'!E59 -> 1319.6 | D88: ='Data Sheet'!F59 -> 1118.5 | E88: ='Data Sheet'!G59 -> 1093.12 | F88: ='Data Sheet'!H59 -> 1586.88 | G88: ='Data Sheet'!I59 -> 1932.62 | H88: ='Data Sheet'!J59 -> 2474.38 | I88: ='Data Sheet'!K59 -> 2290.29
B89: Market cap/Long Term Liabilities(D) | C89: =C87/C88 -> 108.50216 | D89: =D87/D88 -> 142.9149 | E89: =E87/E88 -> 222.65337 | F89: =F87/F88 -> 186.16916 | G89: =G87/G88 -> 137.06619 | H89: =H87/H88 -> 110.35477 | I89: =I87/I88 -> 98.028909
B93: Sales/Total Assets
C94: =C86 -> 43555 | D94: =D86 -> 43921 | E94: =E86 -> 44286 | F94: =F86 -> 44651 | G94: =G86 -> 45016 | H94: =H86 -> 45382 | I94: =I86 -> 45747
B95: Sales | C95: ='Data Sheet'!E17 -> 19240.13 | D95: ='Data Sheet'!F17 -> 20211.25 | E95: ='Data Sheet'!G17 -> 21712.79 | F95: ='Data Sheet'!H17 -> 29101.28 | G95: ='Data Sheet'!I17 -> 34488.59 | H95: ='Data Sheet'!J17 -> 35494.73 | I95: ='Data Sheet'!K17 -> 33905.62
B96: Total Assets | C96: =C82 -> 16248.84 | D96: =D82 -> 16137.97 | E96: =E82 -> 20355.34 | F96: =F82 -> 22958.43 | G96: =G82 -> 25779.33 | H96: =H82 -> 29900.77 | I96: =I82 -> 30355.25
B97: Sales/Total Assets(E) | C97: =C95/C96 -> 1.1840925 | D97: =D95/D96 -> 1.2524035 | E97: =E95/E96 -> 1.0666877 | F97: =F95/F96 -> 1.267564 | G97: =G95/G96 -> 1.3378389 | H97: =H95/H96 -> 1.1870841 | I97: =I95/I96 -> 1.1169607
B99: Altman's Z Score
C100: =C94 -> 43555 | D100: =D94 -> 43921 | E100: =E94 -> 44286 | F100: =F94 -> 44651 | G100: =G94 -> 45016 | H100: =H94 -> 45382 | I100: =I94 -> 45747
B101: Final Score | C101: =(C71*1.2)+(C77*1.4)+(C83*3.3)+(C89*0.6)+(C97*1) -> 67.115456 | D101: =(D71*1.2)+(D77*1.4)+(D83*3.3)+(D89*0.6)+(D97*1) -> 88.012694 | E101: =(E71*1.2)+(E77*1.4)+(E83*3.3)+(E89*0.6)+(E97*1) -> 135.5816 | F101: =(F71*1.2)+(F77*1.4)+(F83*3.3)+(F89*0.6)+(F97*1) -> 113.92459 | G101: =(G71*1.2)+(G77*1.4)+(G83*3.3)+(G89*0.6)+(G97*1) -> 84.659762 | H101: =(H71*1.2)+(H77*1.4)+(H83*3.3)+(H89*0.6)+(H97*1) -> 68.486836 | I101: =(I71*1.2)+(I77*1.4)+(I83*3.3)+(I89*0.6)+(I97*1) -> 60.777502
B102: Financial Stability | C102: =IF(C101<1.81,"Distressed",IF(C101>3,"Strong","Grey Zone")) -> Strong | D102: =IF(D101<1.81,"Distressed",IF(D101>3,"Strong","Grey Zone")) -> Strong | E102: =IF(E101<1.81,"Distressed",IF(E101>3,"Strong","Grey Zone")) -> Strong | F102: =IF(F101<1.81,"Distressed",IF(F101>3,"Strong","Grey Zone")) -> Strong | G102: =IF(G101<1.81,"Distressed",IF(G101>3,"Strong","Grey Zone")) -> Strong | H102: =IF(H101<1.81,"Distressed",IF(H101>3,"Strong","Grey Zone")) -> Strong | I102: =IF(I101<1.81,"Distressed",IF(I101>3,"Strong","Grey Zone")) -> Strong

Sheet DCF>
B2: Calculation of PV of FCFF | E2: ='Intrisic Growth'!I2 -> 45717 | F2: =E2+365 -> 46082 | G2: =F2+365 -> 46447 | H2: =G2+366 -> 46813 | I2: =H2+365 -> 47178 | J2: =I2+365 -> 47543
B4: EBIT | E4: =IFERROR('Data Sheet'!K34-'Data Sheet'!K26,0) -> 5287.61 | F4: =E4*(1+$D$14) -> 6384.7891 | G4: =F4*(1+$D$14) -> 7709.6328 | H4: =G4*(1+$D$14) -> 9309.3816 | I4: =H4*(1+$D$14) -> 11241.078 | J4: =I4*(1+$D$14) -> 13573.602
B5: Tax Rate | E5: 0.25 | F5: =$E$5 -> 0.25 | G5: =$E$5 -> 0.25 | H5: =$E$5 -> 0.25 | I5: =$E$5 -> 0.25 | J5: =$E$5 -> 0.25
B6: EBIT(1-Tax) | E6: =E4*(1-E5) -> 3965.7075 | F6: =E6*(1+$D$14) -> 4788.5918 | G6: =F6*(1+$D$14) -> 5782.2246 | H6: =G6*(1+$D$14) -> 6982.0362 | I6: =H6*(1+$D$14) -> 8430.8087 | J6: =I6*(1+$D$14) -> 10180.202
B7: Less: Reinvestment Rate | E7: 0.4914
B8: Free Cash Flow to Firm(FCFF) | E8: =E6*(1-E7) -> 2016.9588 | F8: =E8*(1+$D$14) -> 2435.4778 | G8: =F8*(1+$D$14) -> 2940.8394 | H8: =G8*(1+$D$14) -> 3551.0636 | I8: =H8*(1+$D$14) -> 4287.9093 | J8: =I8*(1+$D$14) -> 5177.6505
B9: Mid Year Convention | F9: 0.5 | G9: =F9+1 -> 1.5 | H9: =G9+1 -> 2.5 | I9: =H9+1 -> 3.5 | J9: =I9+1 -> 4.5
B10: Discounting Factor | F10: =1/(1+$D$16)^F9 -> 0.9419742 | G10: =1/(1+$D$16)^G9 -> 0.8358282 | H10: =1/(1+$D$16)^H9 -> 0.74164322 | I10: =1/(1+$D$16)^I9 -> 0.65807144 | J10: =1/(1+$D$16)^J9 -> 0.58391691
B12: PV of FCFF | F12: =F8*F10 -> 2294.1572 | G12: =G8*G10 -> 2458.0365 | H12: =H8*H10 -> 2633.6222 | I12: =I8*I10 -> 2821.7506 | J12: =J8*J10 -> 3023.3177
B14: Expected Growth | D14: 0.2075
B15: Terminal Growth | D15: 0.045 | F15: Sensitivy Analysis
B16: WACC | D16: =WACC!J43 -> 0.126995 | F16: =D37 -> 586.37307 | G16: 0.12 | H16: 0.1269 | I16: 0.135 | J16: 0.14
F17: 0.03 | G17: 545.08788 | H17: 514.97547 | I17: 484.67602 | J17: 468.20006
B18: Calculation of Terminal Value | F18: 0.04 | G18: 597.94826 | H18: 560.17347 | I18: 522.83088 | J18: 502.79958
F19: 0.045 | G19: 629.66448 | H19: 586.91147 | I19: 545.08788 | J19: 522.83088
B20: FCFF(n+1) | D20: =J8*(1+D14) -> 6252.013 | F20: 0.05 | G20: 665.9116 | H20: 617.12647 | I20: 569.96335 | J20: 545.08788
B21: WACC | D21: =D16 -> 0.126995 | F21: 0.06 | G21: 756.52939 | H21: 691.10578 | I21: 629.66448 | J21: 597.94826
B22: Terminal Growth Rate | D22: =D15 -> 0.045 | F22: 0.07 | G22: 883.39429 | H22: 791.08837 | I22: 707.73519 | J22: 665.9116
B24: Terminal Value | D24: =D20/(D21-D22) -> 76248.712
B26: Calculation of Enterprise Value
B28: PV of FCFF | D28: =SUM(F12:J12) -> 13230.884
B29: PV Terminal Value | D29: =D24*J10 -> 44522.912
B30: Value of Operating Activities | D30: =SUM(D28:D29) -> 57753.796
B32: Add: Cash | D32: ='Data Sheet'!K69 -> 781.98
B33: Less: debt | D33: =SUM('Raw FS'!N7:N9) -> 2291
B34: Value of Equity | D34: =D30+D32-D33 -> 56244.776
B35: NO. of Shares | D35: ='Data Sheet'!B6 -> 95.91978
B37: Equity Value Per Share | D37: =D34/D35 -> 586.37307
B39: Share Price | D39: ='Data Sheet'!B8 -> 2605.6
B40: Discount/Premium | D40: =D39/D37-1 -> 3.4435874

Sheet WACC
B2: Weighted Average Cost of Capital
B4: All figures are in INR unless stated otherwise.
B6: Peer Comps
G7: Debt/ | H7: Debt/ | I7: Levered | J7: Unlevered
B8: Name | C8: Country | D8: Total Debt | E8: Total Equity | F8: Tax Rate 1 | G8: Equity | H8: Capital | I8: Beta 2 | J8: Beta 3
B10: Asian Paints | C10: India | D10: ='Relative Data'!G3 -> 2291 | E10: ='Beta - Comps'!E4 -> 249928.58 | F10: 0.25 | G10: =D10/E10 -> 0.0091666187 | H10: =D10/(D10+E10) -> 0.0090833551 | I10: ='Beta - Regression'!J13 -> 1.0559519 | J10: =I10/(1+(1-F10)*G10) -> 1.0487419
B11: Berger Paints | C11: India | D11: ='Relative Data'!G4 -> 635.13 | E11: ='Beta - Comps'!E5 -> 63791.48 | F11: =$F$10 -> 0.25 | G11: =D11/E11 -> 0.0099563453 | H11: =D11/(D11+E11) -> 0.0098581937 | I11: 1.04 | J11: =I11/(1+(1-F11)*G11) -> 1.0322916
B12: Kansai Nerolac | C12: India | D12: ='Relative Data'!G5 -> 302.73 | E12: ='Beta - Comps'!E6 -> 17422.14 | F12: =$F$10 -> 0.25 | G12: =D12/E12 -> 0.017376166 | H12: =D12/(D12+E12) -> 0.017079392 | I12: 1.053 | J12: =I12/(1+(1-F12)*G12) -> 1.0394537
B13: JSW Dulux | C13: India | D13: ='Relative Data'!G6 -> 79.1 | E13: ='Beta - Comps'!E7 -> 14647.68 | F13: =$F$10 -> 0.25 | G13: =D13/E13 -> 0.0054001726 | H13: =D13/(D13+E13) -> 0.0053711674 | I13: 0.6 | J13: =I13/(1+(1-F13)*G13) -> 0.59757972
B14: Indigo Paints | C14: India | D14: ='Relative Data'!G7 -> 18.37 | E14: ='Beta - Comps'!E8 -> 4825.19 | F14: =$F$10 -> 0.25 | G14: =D14/E14 -> 0.003807104 | H14: =D14/(D14+E14) -> 0.0037926649 | I14: 1.2 | J14: =I14/(1+(1-F14)*G14) -> 1.1965834
E16: Average | F16: =AVERAGE(F10:F14) -> 0.25 | G16: =AVERAGE(G10:G14) -> 0.0091412813 | H16: =AVERAGE(H10:H14) -> 0.0090369546 | I16: =AVERAGE(I10:I14) -> 0.98979039 | J16: =AVERAGE(J10:J14) -> 0.98293005
E17: Median | F17: =MEDIAN(F10:F14) -> 0.25 | G17: =MEDIAN(G10:G14) -> 0.0091666187 | H17: =MEDIAN(H10:H14) -> 0.0090833551 | I17: =MEDIAN(I10:I14) -> 1.053 | J17: =MEDIAN(J10:J14) -> 1.0394537
B20: Cost of Debt | G20: Cost of Equity
B22: Pre-tax Cost of Debt | E22: 0.076 | G22: Risk Free Rate | J22: 0.0685
B23: Tax Rate | E23: =F17 -> 0.25 | G23: Equity Risk Premium | J23: =Rm!G11-WACC!J22 -> 0.056
B24: After Tax Cost of Debt | E24: =E22*(1-E23) -> 0.057 | G24: Levered Beta 4 | J24: ='Beta - Regression'!J13 -> 1.0559519
G25: Cost of Equity | J25: =J22+(J23*J24) -> 0.12763331
B28: Capital Structure | G28: Levered Beta
D30: Current | E30: Target | G30: Comps Median Unlevered Beta | J30: =J17 -> 1.0394537
B31: Total Debt | C31: =D10 -> 2291 | D31: =C31/$C$33 -> 0.0090833551 | E31: =H16 -> 0.0090369546 | G31: Target Debt/ Equity | J31: =E35 -> 0.0091193659
B32: Market Capitalization | C32: =E10 -> 249928.58 | D32: =C32/$C$33 -> 0.99091664 | E32: =E33-E31 -> 0.99096305 | G32: Tax Rate | J32: =E23 -> 0.25
B33: Total Capitalization | C33: =SUM(C31:C32) -> 252219.58 | D33: =C33/$C$33 -> 1 | E33: =D33 -> 1 | G33: Levered Beta | J33: =J30*(1+(1-J31)*J32) -> 1.2969473
B35: Debt / Equity | D35: =D31/D32 -> 0.0091666187 | E35: =E31/E32 -> 0.0091193659 | G35: Weighted Average Cost of Capital
B37: 1. Tax Rate considered as Marginal Tax Rate for the country | G37: Cost of Equity | J37: =J25 -> 0.12763331
B38: 2. Levered Beta is based on 5 year monthly data | G38: Equity Weight | J38: =E32 -> 0.99096305
B39: 3. Unlevered Beta = Levered Beta/(1+(1-Tax Rate) x Debt/Equity)
B40: 4. Levered Beta = Unlevered Beta/(1+(1-Tax Rate) x Debt/Equity) | G40: Cost of Debt | J40: =E24 -> 0.057
B41: 5.All Beta are calculated on 5 year monthly basis | G41: Debt Weight | J41: =E31 -> 0.0090369546
G43: WACC | J43: =(J37*J38)+(J40*J41) -> 0.126995

Sheet Intrisic Growth
A2: # | B2: Calculation of ROIC | E2: ='Raw FS'!J$2 -> 44256 | F2: ='Raw FS'!K$2 -> 44621 | G2: ='Raw FS'!L$2 -> 44986 | H2: ='Raw FS'!M$2 -> 45352 | I2: ='Raw FS'!N$2 -> 45717
B4: Current Assets
B5: ='Raw FS'!B35 -> Inventories | E5: ='Raw FS'!J35 -> 3799 | F5: ='Raw FS'!K35 -> 6153 | G5: ='Raw FS'!L35 -> 6211 | H5: ='Raw FS'!M35 -> 5923 | I5: ='Raw FS'!N35 -> 6719
B6: ='Raw FS'!B36 -> Trade receivables | E6: ='Raw FS'!J36 -> 2602 | F6: ='Raw FS'!K36 -> 3871 | G6: ='Raw FS'!L36 -> 4637 | H6: ='Raw FS'!M36 -> 4889 | I6: ='Raw FS'!N36 -> 4314
B7: ='Raw FS'!B38 -> Loans n Advances | E7: ='Raw FS'!J38 -> 11 | F7: ='Raw FS'!K38 -> 8 | G7: ='Raw FS'!L38 -> 12 | H7: ='Raw FS'!M38 -> 17 | I7: ='Raw FS'!N38 -> 22
B8: ='Raw FS'!B39 -> Other asset items | E8: ='Raw FS'!J39 -> 2555 | F8: ='Raw FS'!K39 -> 2869 | G8: ='Raw FS'!L39 -> 3024 | H8: ='Raw FS'!M39 -> 3555 | I8: ='Raw FS'!N39 -> 3319
B9: Total Current Assets | E9: =SUM(E5:E8) -> 8967 | F9: =SUM(F5:F8) -> 12901 | G9: =SUM(G5:G8) -> 13884 | H9: =SUM(H5:H8) -> 14384 | I9: =SUM(I5:I8) -> 14374
B11: Current Liabilities
B12: ='Raw FS'!B13 -> Trade Payables | E12: ='Raw FS'!J13 -> 3379 | F12: ='Raw FS'!K13 -> 4164 | G12: ='Raw FS'!L13 -> 3635 | H12: ='Raw FS'!M13 -> 3831 | I12: ='Raw FS'!N13 -> 3848
B13: ='Raw FS'!B14 -> Advance from Customers | E13: ='Raw FS'!J14 -> 41 | F13: ='Raw FS'!K14 -> 76 | G13: ='Raw FS'!L14 -> 108 | H13: ='Raw FS'!M14 -> 154 | I13: ='Raw FS'!N14 -> 173
B14: ='Raw FS'!B15 -> Other liability items | E14: ='Raw FS'!J15 -> 2613 | F14: ='Raw FS'!K15 -> 2932 | G14: ='Raw FS'!L15 -> 3657 | H14: ='Raw FS'!M15 -> 4017 | I14: ='Raw FS'!N15 -> 3985
B15: Total Current Liabilities | E15: =SUM(E12:E14) -> 6033 | F15: =SUM(F12:F14) -> 7172 | G15: =SUM(G12:G14) -> 7400 | H15: =SUM(H12:H14) -> 8002 | I15: =SUM(I12:I14) -> 8006
A17: # | B17: Net Working Capital | E17: =E9-E15 -> 2934 | F17: =F9-F15 -> 5729 | G17: =G9-G15 -> 6484 | H17: =H9-H15 -> 6382 | I17: =I9-I15 -> 6368
B19: Non Current Assets
B20: ='Raw FS'!B19 -> Land | E20: ='Raw FS'!J19 -> 644 | F20: ='Raw FS'!K19 -> 644 | G20: ='Raw FS'!L19 -> 804 | H20: ='Raw FS'!M19 -> 1126 | I20: ='Raw FS'!N19 -> 1050
B21: ='Raw FS'!B20 -> Building | E21: ='Raw FS'!J20 -> 2249 | F21: ='Raw FS'!K20 -> 2325 | G21: ='Raw FS'!L20 -> 2883 | H21: ='Raw FS'!M20 -> 3390 | I21: ='Raw FS'!N20 -> 4136
B22: ='Raw FS'!B21 -> Plant Machinery | E22: ='Raw FS'!J21 -> 4340 | F22: ='Raw FS'!K21 -> 4531 | G22: ='Raw FS'!L21 -> 4825 | H22: ='Raw FS'!M21 -> 5422 | I22: ='Raw FS'!N21 -> 7576
B23: ='Raw FS'!B22 -> Equipments | E23: ='Raw FS'!J22 -> 243 | F23: ='Raw FS'!K22 -> 253 | G23: ='Raw FS'!L22 -> 270 | H23: ='Raw FS'!M22 -> 298 | I23: ='Raw FS'!N22 -> 325
B24: ='Raw FS'!B23 -> Furniture n fittings | E24: ='Raw FS'!J23 -> 99 | F24: ='Raw FS'!K23 -> 113 | G24: ='Raw FS'!L23 -> 146 | H24: ='Raw FS'!M23 -> 175 | I24: ='Raw FS'!N23 -> 203
B25: ='Raw FS'!B24 -> Vehicles | E25: ='Raw FS'!J24 -> 38 | F25: ='Raw FS'!K24 -> 32 | G25: ='Raw FS'!L24 -> 36 | H25: ='Raw FS'!M24 -> 40 | I25: ='Raw FS'!N24 -> 39
B26: ='Raw FS'!B25 -> Intangible Assets | E26: ='Raw FS'!J25 -> 476 | F26: ='Raw FS'!K25 -> 345 | G26: ='Raw FS'!L25 -> 422 | H26: ='Raw FS'!M25 -> 850 | I26: ='Raw FS'!N25 -> 827
B27: ='Raw FS'!B26 -> Other fixed assets | E27: ='Raw FS'!J26 -> 302 | F27: ='Raw FS'!K26 -> 294 | G27: ='Raw FS'!L26 -> 289 | H27: ='Raw FS'!M26 -> 321 | I27: ='Raw FS'!N26 -> 328
B29: Gross Block | E29: =SUM(E20:E28) -> 8391 | F29: =SUM(F20:F28) -> 8537 | G29: =SUM(G20:G28) -> 9675 | H29: =SUM(H20:H28) -> 11622 | I29: =SUM(I20:I28) -> 14484
B30: Accumulated Depreciation | E30: =-'Raw FS'!J28 -> -2533 | F30: =-'Raw FS'!K28 -> -3019 | G30: =-'Raw FS'!L28 -> -3905 | H30: =-'Raw FS'!M28 -> -4475 | I30: =-'Raw FS'!N28 -> -5264
A31: # | B31: Net Non Current Assets | E31: =SUM(E29:E30) -> 5858 | F31: =SUM(F29:F30) -> 5518 | G31: =SUM(G29:G30) -> 5770 | H31: =SUM(H29:H30) -> 7147 | I31: =SUM(I29:I30) -> 9220
A33: # | B33: Invested Capital | E33: =E31+E17 -> 8792 | F33: =F31+F17 -> 11247 | G33: =G31+G17 -> 12254 | H33: =H31+H17 -> 13529 | I33: =I31+I17 -> 15588
B34: EBIT | E34: =(HistoricalFS!H27+HistoricalFS!H21) -> 4064.33 | F34: =(HistoricalFS!I27+HistoricalFS!I21) -> 3987.25 | G34: =(HistoricalFS!J27+HistoricalFS!J21) -> 5401.82 | H34: =(HistoricalFS!K27+HistoricalFS!K21) -> 6731.98 | I34: =(HistoricalFS!L27+HistoricalFS!L21) -> 4979.87
A36: # | B36: ROIC | E36: =E34/E33 -> 0.46227593 | F36: =F34/F33 -> 0.35451676 | G36: =G34/G33 -> 0.44082096 | H36: =H34/H33 -> 0.49759627 | I36: =I34/I33 -> 0.31946818
A39: # | B39: Calculation of Reinvestment Rate | E39: ='Raw FS'!J$2 -> 44256 | F39: ='Raw FS'!K$2 -> 44621 | G39: ='Raw FS'!L$2 -> 44986 | H39: ='Raw FS'!M$2 -> 45352 | I39: ='Raw FS'!N$2 -> 45717
B41: Net Capex | E41: =-SUM('Raw FS'!J54:J55) -> 261 | F41: =-SUM('Raw FS'!K54:K55) -> 511 | G41: =-SUM('Raw FS'!L54:L55) -> 1420 | H41: =-SUM('Raw FS'!M54:M55) -> 2491 | I41: =-SUM('Raw FS'!N54:N55) -> 1820
B42: Change in Working Capital | F42: =F17-E17 -> 2795 | G42: =G17-F17 -> 755 | H42: =H17-G17 -> -102 | I42: =I17-H17 -> -14
B44: EBIT | E44: =E34 -> 4064.33 | F44: =F34 -> 3987.25 | G44: =G34 -> 5401.82 | H44: =H34 -> 6731.98 | I44: =I34 -> 4979.87
B45: Marginal Tax Rate | E45: 0.25 | F45: 0.25 | G45: 0.25 | H45: 0.25 | I45: 0.25
B46: EBIT(1-T) | E46: =E44*(1-E45) -> 3048.2475 | F46: =F44*(1-F45) -> 2990.4375 | G46: =G44*(1-G45) -> 4051.365 | H46: =H44*(1-H45) -> 5048.985 | I46: =I44*(1-I45) -> 3734.9025
B48: Reinvestment | F48: =SUM(F41:F42) -> 3306 | G48: =SUM(G41:G42) -> 2175 | H48: =SUM(H41:H42) -> 2389 | I48: =SUM(I41:I42) -> 1806
B50: Reinvestment Rate | F50: =F48/F46 -> 1.1055239 | G50: =G48/G46 -> 0.5368561 | H50: =H48/H46 -> 0.47316441 | I50: =I48/I46 -> 0.48354676
H52: 4 Year Average | I52: =AVERAGE(F50:I50) -> 0.64977278
H53: 4 Year Median | I53: =MEDIAN(F50:I50) -> 0.51020143
A55: # | B55: Calculation of Growth Rate | E55: ='Raw FS'!J$2 -> 44256 | F55: ='Raw FS'!K$2 -> 44621 | G55: ='Raw FS'!L$2 -> 44986 | H55: ='Raw FS'!M$2 -> 45352 | I55: ='Raw FS'!N$2 -> 45717
B57: Reinvestment Rate | F57: =F50 -> 1.1055239 | G57: =G50 -> 0.5368561 | H57: =H50 -> 0.47316441 | I57: =I50 -> 0.48354676
B58: ROIC | F58: =F36 -> 0.35451676 | G58: =G36 -> 0.44082096 | H58: =H36 -> 0.49759627 | I58: =I36 -> 0.31946818
B60: Intrinsic Growth | F60: =F57*F58 -> 0.39192674 | G60: =G57*G58 -> 0.23665742 | H60: =H57*H58 -> 0.23544485 | I60: =I57*I58 -> 0.1544778
H62: 4 Year Average | I62: =AVERAGE(F60:I60) -> 0.2546267
H63: 4 Year Median | I63: =MEDIAN(F60:I60) -> 0.23605113

Sheet Beta - Regression
E2: needs correction
B3: Regression Beta - 5 Years Monthly
B5: ='Data Sheet'!B1 &" - " & "Weekly Returns" -> ASIAN PAINTS LTD - Weekly Returns | F5: NIFTY Returns | I5: Beta Drifting | L5: Beta 1 | M5: =SLOPE(D8:D112,G8:G112) -> 1.0746026
B6: Date | C6: Closing Price | D6: Return | F6: Closing Price | G6: Return | L6: Beta 2 | M6: =_xlfn.COVARIANCE.S(D7:D112,G7:G112)/VAR(G7:G112) -> 1.0746026
B7: 46174 | C7: 2645.2 | F7: 24021.65 | I7: Levered Raw Beta | J7: =M5 -> 1.0746026
B8: 46143 | C8: 2671.6 | D8: =C8/C7-1 -> 0.0099803418 | F8: 23547.75 | G8: =F8/F7-1 -> -0.019728037 | I8: Raw Beta Weight | J8: 0.75 | L8: Beta 3
B9: 46113 | C9: 2444.5 | D9: =C9/C8-1 -> -0.08500524 | F9: 23997.55 | G9: =F9/F8-1 -> 0.019101613
B10: 46082 | C10: 2165.2 | D10: =C10/C9-1 -> -0.11425649 | F10: 22331.4 | G10: =F10/F9-1 -> -0.069430004 | I10: Market Beta | J10: 1
B11: 46054 | C11: 2376.2 | D11: =C11/C10-1 -> 0.097450582 | F11: 25178.65 | G11: =F11/F10-1 -> 0.12749984 | I11: Market Beta Weight | J11: 0.25
B12: 46023 | C12: 2428.3 | D12: =C12/C11-1 -> 0.021925764 | F12: 25320.65 | G12: =F12/F11-1 -> 0.0056396987
B13: 45992 | C13: 2769.5 | D13: =C13/C12-1 -> 0.14050982 | F13: 26129.6 | G13: =F13/F12-1 -> 0.031948232 | I13: Adjusted Beta | J13: =(J7*J8)+(J10*J11) -> 1.0559519
B14: 45962 | C14: 2874.4 | D14: =C14/C13-1 -> 0.037876873 | F14: 26202.95 | G14: =F14/F13-1 -> 0.0028071612
B15: 45931 | C15: 2510.8 | D15: =C15/C14-1 -> -0.12649596 | F15: 25722.1 | G15: =F15/F14-1 -> -0.018350987
B16: 45901 | C16: 2350 | D16: =C16/C15-1 -> -0.064043333 | F16: 24611.1 | G16: =F16/F15-1 -> -0.04319243
B17: 45870 | C17: 2518.6 | D17: =C17/C16-1 -> 0.071744681 | F17: 24426.85 | G17: =F17/F16-1 -> -0.0074864594
B18: 45839 | C18: 2396.1 | D18: =C18/C17-1 -> -0.048638132 | F18: 24768.35 | G18: =F18/F17-1 -> 0.013980517
B19: 45809 | C19: 2341.1 | D19: =C19/C18-1 -> -0.022953967 | F19: 25517.05 | G19: =F19/F18-1 -> 0.030228094
B20: 45778 | C20: 2259.1 | D20: =C20/C19-1 -> -0.03502627 | F20: 24750.7 | G20: =F20/F19-1 -> -0.03003286
B21: 45748 | C21: 2425.7 | D21: =C21/C20-1 -> 0.073746182 | F21: 24334.2 | G21: =F21/F20-1 -> -0.016827807
B22: 45717 | C22: 2340.65 | D22: =C22/C21-1 -> -0.035062044 | F22: 23519.35 | G22: =F22/F21-1 -> -0.033485794
B23: 45689 | C23: 2179.75 | D23: =C23/C22-1 -> -0.068741589 | F23: 22124.7 | G23: =F23/F22-1 -> -0.059297982
B24: 45658 | C24: 2300.8 | D24: =C24/C23-1 -> 0.055533892 | F24: 23508.4 | G24: =F24/F23-1 -> 0.062540961
B25: 45627 | C25: 2281.35 | D25: =C25/C24-1 -> -0.0084535814 | F25: 23644.8 | G25: =F25/F24-1 -> 0.0058021813
... B66: 44378 | C66: 2958.45 | D66: =C66/C65-1 -> -0.075874241 | F66: 15763.05 | G66: =F66/F65-1 -> -0.079916765

Sheet Relative valuation
B3: Amount in crores
B4: Comparable Company Valuations
D6: Market Data | K6: Financials | O6: Valuation
B7: Company | C7: Ticker | D7: Share prize | E7: Shares Outstanding | F7: Equity Value | G7: Net Debt | H7: Enterprise Value | K7: Revenue | L7: EBITDA | M7: Net Income | O7: EV/Revenue | P7: EV/EBITDA | Q7: P/E
B9: Asian Paints | D9: ='Relative Data'!D3 -> 2605.6 | E9: ='Relative Data'!E3 -> 95.91978 | F9: =E9*D9 -> 249928.58 | G9: ='Relative Data'!I3 -> 1509.02 | H9: =G9+F9 -> 251437.6 | K9: ='Data Sheet'!K17 -> 33905.62 | L9: ='Relative Data'!L3 -> 6313.95 | M9: ='Relative Data'!M3 -> 3667.23 | O9: ='Relative Data'!J3/'Relative Data'!K3 -> 7.4158089 | P9: ='Relative Data'!$J3/'Relative valuation'!L9 -> 39.822552 | Q9: ='Relative Data'!O3 -> 68.151869
B10: Berger Paints | D10: 545.75 | E10: 116.60027 | F10: =E10*D10 -> 63634.6 | G10: 329.82 | H10: =G10+F10 -> 63964.42 | K10: ='Relative Data'!K4 -> 11880.25 | L10: ='Relative Data'!L4 -> 1990.8005 | M10: ='Relative Data'!M4 -> 1165.8959 | O10: ='Relative Data'!$J4/'Relative valuation'!K10 -> 5.3840971 | P10: ='Relative Data'!$J4/'Relative valuation'!L10 -> 32.13 | Q10: ='Relative Data'!O4 -> 54.58
B11: Kansai Nerolac | D11: 216 | E11: 80.871435 | F11: =E11*D11 -> 17468.23 | G11: 76.95 | H11: =G11+F11 -> 17545.18 | K11: ='Relative Data'!K5 -> 8051.91 | L11: ='Relative Data'!L5 -> 1049.3529 | M11: ='Relative Data'!M5 -> 579.18534 | O11: ='Relative Data'!$J5/'Relative valuation'!K11 -> 2.1790085 | P11: ='Relative Data'!$J5/'Relative valuation'!L11 -> 16.72 | Q11: ='Relative Data'!O5 -> 30.16
B12: JSW Dulux | D12: 3205.35 | E12: 4.5540331 | F12: =E12*D12 -> 14597.27 | G12: -244.6 | H12: =G12+F12 -> 14352.67 | K12: ='Relative Data'!K6 -> 3599.2 | L12: ='Relative Data'!L6 -> 521.15723 | M12: ='Relative Data'!M6 -> 361.13978 | O12: ='Relative Data'!$J6/'Relative valuation'!K12 -> 3.9877389 | P12: ='Relative Data'!$J6/'Relative valuation'!L12 -> 27.54 | Q12: ='Relative Data'!O6 -> 40.42
B13: Indigo Paints | D13: 1060.5 | E13: 4.7675719 | F13: =E13*D13 -> 5056.01 | G13: -10.18 | H13: =G13+F13 -> 5045.83 | K13: ='Relative Data'!K7 -> 1330.12 | L13: ='Relative Data'!L7 -> 258.89328 | M13: ='Relative Data'!M7 -> 149.67466 | O13: ='Relative Data'!$J7/'Relative valuation'!K13 -> 3.7935149 | P13: ='Relative Data'!$J7/'Relative valuation'!L13 -> 19.49 | Q13: ='Relative Data'!O7 -> 33.78
B15: High | O15: =MAX(O9:O13) -> 7.4158089 | P15: =MAX(P9:P13) -> 39.822552 | Q15: =MAX(Q9:Q13) -> 68.151869
B16: 75th Percentile | O16: =QUARTILE(O9:O13,3) -> 5.3840971 | P16: =QUARTILE(P9:P13,3) -> 32.13 | Q16: =QUARTILE(Q9:Q13,3) -> 54.58
B17: Average | O17: =AVERAGE(O9:O13) -> 4.5520337 | P17: =AVERAGE(P9:P13) -> 27.14051 | Q17: =AVERAGE(Q9:Q13) -> 45.418374
B18: Median | O18: =MEDIAN(O9:O13) -> 3.9877389 | P18: =MEDIAN(P9:P13) -> 27.54 | Q18: =MEDIAN(Q9:Q13) -> 40.42
B19: 25th Percentile | O19: =QUARTILE(O9:O13,1) -> 3.7935149 | P19: =QUARTILE(P9:P13,1) -> 19.49 | Q19: =QUARTILE(Q9:Q13,1) -> 33.78
B20: Low | O20: =MIN(O9:O13) -> 2.1790085 | P20: =MIN(P9:P13) -> 16.72 | Q20: =MIN(Q9:Q13) -> 30.16
B22: Comparable Company Valuations | O22: EV/Revenue | P22: EV/EBITDA | Q22: P/E
B24: Implied Enterprise Value | O24: =O18*K9 -> 135206.76 | P24: =P18*L9 -> 173886.18 | Q24: =Q26+Q25 -> 149738.46
B25: Net Debt | O25: =$G$9 -> 1509.02 | P25: =$G$9 -> 1509.02 | Q25: =$G$9 -> 1509.02
B26: Implied Market Value | O26: =O24-O25 -> 133697.74 | P26: =P24-P25 -> 172377.16 | Q26: =Q18*M9 -> 148229.44
B27: Shares Outstanding | O27: =$E$9 -> 95.91978 | P27: =$E$9 -> 95.91978 | Q27: =$E$9 -> 95.91978
B29: Implied value per share | O29: =O26/O27 -> 1393.8495 | P29: =P26/P27 -> 1797.0971 | Q29: =Q26/Q27 -> 1545.348
B31: Source: The Valuation School, Screener.in
O32: =IF(O29>$D$9,"Undervalued","Overvalued") -> Overvalued | P32: =IF(P29>$D$9,"Undervalued","Overvalued") -> Overvalued | Q32: =IF(Q29>$D$9,"Undervalued","Overvalued") -> Overvalued

Sheet Beta - Comps
B3: S.No. | C3: Name | D3: CMP Rs. | E3: Mar Cap Rs.Cr. | F3: Debt Rs.Cr. | G3: Debt / Eq
B4: 1 | C4: Asian Paints | D4: ='Data Sheet'!B8 -> 2605.6 | E4: ='Data Sheet'!B9 -> 249928.58 | F4: =SUM('Raw FS'!N7:N9) -> 2291 | G4: =F4/E4 -> 0.0091666187
B5: 2 | C5: Berger Paints | D5: 546.25 | E5: 63791.48 | F5: 635.13 | G5: =F5/E5 -> 0.0099563453
B6: 3 | C6: Kansai Nerolac | D6: 215.58 | E6: 17422.14 | F6: 302.73 | G6: =F6/E6 -> 0.017376166
B7: 4 | C7: JSW Dulux | D7: 3205.8 | E7: 14647.68 | F7: 79.1 | G7: =F7/E7 -> 0.0054001726
B8: 5 | C8: Indigo Paints | D8: 1010.05 | E8: 4825.19 | F8: 18.37 | G8: =F8/E8 -> 0.003807104

Sheet Rm
B6: Return on Markets - Nifty 50
B8: Year | C8: Annual
B9: 2011 | C9: -0.2462 | E9: Average Return | G9: =AVERAGE(C9:C23) -> 0.1106
B10: 2012 | C10: 0.277 | E10: Dividend Yield | G10: 0.0139
B11: 2013 | C11: 0.0676 | E11: Total Market Returns | G11: =SUM(G10,G9) -> 0.1245
B12: 2014 | C12: 0.3139
B13: 2015 | C13: -0.0406
B14: 2016 | C14: 0.0301
B15: 2017 | C15: 0.2865
B16: 2018 | C16: 0.0315
B17: 2019 | C17: 0.1202
B18: 2020 | C18: 0.1417
B19: 2021 | C19: 0.2412
B20: 2022 | C20: 0.0432
B21: 2023 | C21: 0.2003
B22: 2024 | C22: 0.0876
B23: 2025 | C23: 0.105

Sheet Analysis
B3: ='Data Sheet'!B1 -> ASIAN PAINTS LTD
B4: =CONCATENATE("(",_xlfn.XLOOKUP(B3,'List Of Stocks'!B2:B5442,'List Of Stocks'!D2:D5442), " | ","BSE Code: ",_xlfn.XLOOKUP(Analysis!B3,'List Of Stocks'!B2:B5442,'List Of Stocks'!C2:C5442,,0)," ) ") -> (ASIANPAINT | BSE Code: 500820 )
B5: =CONCATENATE("INR", " ",'Data Sheet'!B8) -> INR 2605.6
B6: ="52 Week" & " "&"("&"High -" & " INR " &'Football Field Analysis'!Q10 & " " &"LOW - " & " INR " &'Football Field Analysis'!N10 &")" -> 52 Week (High - INR 2985.7 LOW - INR 2115)
B8: About The Company
B9: Asian Paints Ltd is an Indian multinational paint company, headquartered in Mumbai.The company is engaged in the business of manufacturing, selling and distribution of paints, coatings, products related to home décor, bath fittings and providing related services. Asian Paints is India's largest paints company by market share.The company has 27 paint manufacturing facilities in 15 countries, servicing consumers in over 60 countries. Asian Paints is also present in the home improvement and décor space in India
B16: Financial Summary
B67: Return On Equity(ROE)
C68: =HistoricalFS!F3 -> 43555 | D68: =HistoricalFS!G3 -> 43921 | E68: =HistoricalFS!H3 -> 44286 | F68: =HistoricalFS!I3 -> 44651 | G68: =HistoricalFS!J3 -> 45016 | H68: =HistoricalFS!K3 -> 45382 | I68: =HistoricalFS!L3 -> 45747
B69: Net Profit | C69: =IFERROR('Data Sheet'!E30,0) -> 2155.92 | D69: =IFERROR('Data Sheet'!F30,0) -> 2705.17 | E69: =IFERROR('Data Sheet'!G30,0) -> 3139.29 | F69: =IFERROR('Data Sheet'!H30,0) -> 3030.57 | G69: =IFERROR('Data Sheet'!I30,0) -> 4106.45 | H69: =IFERROR('Data Sheet'!J30,0) -> 5460.23 | I69: =IFERROR('Data Sheet'!K30,0) -> 3667.23
B70: Average Shareholder Equity | C70: =IFERROR((('Data Sheet'!E57+'Data Sheet'!E58)+('Data Sheet'!D58+'Data Sheet'!D57))/2,0) -> 8940.39 | D70: =IFERROR((('Data Sheet'!F57+'Data Sheet'!F58)+('Data Sheet'!E58+'Data Sheet'!E57))/2,0) -> 9800.355 | E70: =IFERROR((('Data Sheet'!G57+'Data Sheet'!G58)+('Data Sheet'!F58+'Data Sheet'!F57))/2,0) -> 11468.225 | F70: =IFERROR((('Data Sheet'!H57+'Data Sheet'!H58)+('Data Sheet'!G58+'Data Sheet'!G57))/2,0) -> 13308.925 | G70: =IFERROR((('Data Sheet'!I57+'Data Sheet'!I58)+('Data Sheet'!H58+'Data Sheet'!H57))/2,0) -> 14901.895 | H70: =IFERROR((('Data Sheet'!J57+'Data Sheet'!J58)+('Data Sheet'!I58+'Data Sheet'!I57))/2,0) -> 17360.265 | I70: =IFERROR((('Data Sheet'!K57+'Data Sheet'!K58)+('Data Sheet'!J58+'Data Sheet'!J57))/2,0) -> 19064.055
B71: Return On Equity | C71: =C69/C70 -> 0.24114384 | D71: =D69/D70 -> 0.27602776 | E71: =E69/E70 -> 0.27373809 | F71: =F69/F70 -> 0.2277096 | G71: =G69/G70 -> 0.27556562 | H71: =H69/H70 -> 0.31452458 | I71: =I69/I70 -> 0.19236359
B73: ROE - Dupont Equation
C74: =C68 -> 43555 | D74: =D68 -> 43921 | E74: =E68 -> 44286 | F74: =F68 -> 44651 | G74: =G68 -> 45016 | H74: =H68 -> 45382 | I74: =I68 -> 45747
B75: =B69 -> Net Profit | C75: =C69 -> 2155.92 | D75: =D69 -> 2705.17 | E75: =E69 -> 3139.29 | F75: =F69 -> 3030.57 | G75: =G69 -> 4106.45 | H75: =H69 -> 5460.23 | I75: =I69 -> 3667.23
B76: Revenue | C76: =IFERROR('Data Sheet'!E17,0) -> 19240.13 | D76: =IFERROR('Data Sheet'!F17,0) -> 20211.25 | E76: =IFERROR('Data Sheet'!G17,0) -> 21712.79 | F76: =IFERROR('Data Sheet'!H17,0) -> 29101.28 | G76: =IFERROR('Data Sheet'!I17,0) -> 34488.59 | H76: =IFERROR('Data Sheet'!J17,0) -> 35494.73 | I76: =IFERROR('Data Sheet'!K17,0) -> 33905.62
B77: Net Profit Margin(A) | C77: =C75/C76 -> 0.1120533 | D77: =D75/D76 -> 0.13384476 | E77: =E75/E76 -> 0.14458252 | F77: =F75/F76 -> 0.10413872 | G77: =G75/G76 -> 0.11906691 | H77: =H75/H76 -> 0.15383213 | I77: =I75/I76 -> 0.10815995
C79: =C74 -> 43555 | D79: =D74 -> 43921 | E79: =E74 -> 44286 | F79: =F74 -> 44651 | G79: =G74 -> 45016 | H79: =H74 -> 45382 | I79: =I74 -> 45747
B80: Revenue | C80: =C76 -> 19240.13 | D80: =D76 -> 20211.25 | E80: =E76 -> 21712.79 | F80: =F76 -> 29101.28 | G80: =G76 -> 34488.59 | H80: =H76 -> 35494.73 | I80: =I76 -> 33905.62
B81: Average Total Assets | C81: =IFERROR(('Data Sheet'!E66+'Data Sheet'!D66)/2,0) -> 15006.16 | D81: =IFERROR(('Data Sheet'!F66+'Data Sheet'!E66)/2,0) -> 16193.405 | E81: =IFERROR(('Data Sheet'!G66+'Data Sheet'!F66)/2,0) -> 18246.655 | F81: =IFERROR(('Data Sheet'!H66+'Data Sheet'!G66)/2,0) -> 21656.885 | G81: =IFERROR(('Data Sheet'!I66+'Data Sheet'!H66)/2,0) -> 24368.88 | H81: =IFERROR(('Data Sheet'!J66+'Data Sheet'!I66)/2,0) -> 27840.05 | I81: =IFERROR(('Data Sheet'!K66+'Data Sheet'!J66)/2,0) -> 30128.01
B82: Asset Turnover Ratio(B) | C82: =C80/C81 -> 1.2821488 | D82: =D80/D81 -> 1.2481161 | E82: =E80/E81 -> 1.18996 | F82: =F80/F81 -> 1.3437426 | G82: =G80/G81 -> 1.4152719 | H82: =H80/H81 -> 1.2749521 | I82: =I80/I81 -> 1.1253853
C84: =C79 -> 43555 | D84: =D79 -> 43921 | E84: =E79 -> 44286 | F84: =F79 -> 44651 | G84: =G79 -> 45016 | H84: =H79 -> 45382 | I84: =I79 -> 45747
B85: Average Total Assets | C85: =IFERROR(('Data Sheet'!E66+'Data Sheet'!D66)/2,0) -> 15006.16 | D85: =IFERROR(('Data Sheet'!F66+'Data Sheet'!E66)/2,0) -> 16193.405 | E85: =IFERROR(('Data Sheet'!G66+'Data Sheet'!F66)/2,0) -> 18246.655 | F85: =IFERROR(('Data Sheet'!H66+'Data Sheet'!G66)/2,0) -> 21656.885 | G85: =IFERROR(('Data Sheet'!I66+'Data Sheet'!H66)/2,0) -> 24368.88 | H85: =IFERROR(('Data Sheet'!J66+'Data Sheet'!I66)/2,0) -> 27840.05 | I85: =IFERROR(('Data Sheet'!K66+'Data Sheet'!J66)/2,0) -> 30128.01
B86: Average Shareholder Equity | C86: =IFERROR((('Data Sheet'!E57+'Data Sheet'!E58)+('Data Sheet'!D58+'Data Sheet'!D57))/2,0) -> 8940.39 | D86: =IFERROR((('Data Sheet'!F57+'Data Sheet'!F58)+('Data Sheet'!E58+'Data Sheet'!E57))/2,0) -> 9800.355 | E86: =IFERROR((('Data Sheet'!G57+'Data Sheet'!G58)+('Data Sheet'!F58+'Data Sheet'!F57))/2,0) -> 11468.225 | F86: =IFERROR((('Data Sheet'!H57+'Data Sheet'!H58)+('Data Sheet'!G58+'Data Sheet'!G57))/2,0) -> 13308.925 | G86: =IFERROR((('Data Sheet'!I57+'Data Sheet'!I58)+('Data Sheet'!H58+'Data Sheet'!H57))/2,0) -> 14901.895 | H86: =IFERROR((('Data Sheet'!J57+'Data Sheet'!J58)+('Data Sheet'!I58+'Data Sheet'!I57))/2,0) -> 17360.265 | I86: =IFERROR((('Data Sheet'!K57+'Data Sheet'!K58)+('Data Sheet'!J58+'Data Sheet'!J57))/2,0) -> 19064.055
B87: Financial Leverage(C) | C87: =C85/C86 -> 1.6784682 | D87: =D85/D86 -> 1.6523284 | E87: =E85/E86 -> 1.5910618 | F87: =F85/F86 -> 1.6272453 | G87: =G85/G86 -> 1.6352873 | H87: =H85/H86 -> 1.603665 | I87: =I85/I86 -> 1.5803569
B89: Return On Equity(A*B*C) | C89: =C87*C82*C77 -> 0.24114384 | D89: =D87*D82*D77 -> 0.27602776 | E89: =E87*E82*E77 -> 0.27373809 | F89: =F87*F82*F77 -> 0.2277096 | G89: =G87*G82*G77 -> 0.27556562 | H89: =H87*H82*H77 -> 0.31452458 | I89: =I87*I82*I77 -> 0.19236359
B91: Return On Asset(ROA)
C92: =C84 -> 43555 | D92: =D84 -> 43921 | E92: =E84 -> 44286 | F92: =F84 -> 44651 | G92: =G84 -> 45016 | H92: =H84 -> 45382 | I92: =I84 -> 45747
B93: Net Profit | C93: =C75 -> 2155.92 | D93: =D75 -> 2705.17 | E93: =E75 -> 3139.29 | F93: =F75 -> 3030.57 | G93: =G75 -> 4106.45 | H93: =H75 -> 5460.23 | I93: =I75 -> 3667.23
B94: =B85 -> Average Total Assets | C94: =C85 -> 15006.16 | D94: =D85 -> 16193.405 | E94: =E85 -> 18246.655 | F94: =F85 -> 21656.885 | G94: =G85 -> 24368.88 | H94: =H85 -> 27840.05 | I94: =I85 -> 30128.01
B95: Return On Asset | C95: =C93/C94 -> 0.143669 | D95: =D93/D94 -> 0.16705381 | E95: =E93/E94 -> 0.17204742 | F95: =F93/F94 -> 0.13993564 | G95: =G93/G94 -> 0.16851205 | H95: =H93/H94 -> 0.1961286 | I95: =I93/I94 -> 0.12172161
B97: ROA - Dupont Analysis
C98: =C92 -> 43555 | D98: =D92 -> 43921 | E98: =E92 -> 44286 | F98: =F92 -> 44651 | G98: =G92 -> 45016 | H98: =H92 -> 45382 | I98: =I92 -> 45747
B99: Net Profit | C99: =C93 -> 2155.92 | D99: =D93 -> 2705.17 | E99: =E93 -> 3139.29 | F99: =F93 -> 3030.57 | G99: =G93 -> 4106.45 | H99: =H93 -> 5460.23 | I99: =I93 -> 3667.23
B100: Revenue | C100: =C80 -> 19240.13 | D100: =D80 -> 20211.25 | E100: =E80 -> 21712.79 | F100: =F80 -> 29101.28 | G100: =G80 -> 34488.59 | H100: =H80 -> 35494.73 | I100: =I80 -> 33905.62
B101: Net Profit Margin(A) | C101: =C99/C100 -> 0.1120533 | D101: =D99/D100 -> 0.13384476 | E101: =E99/E100 -> 0.14458252 | F101: =F99/F100 -> 0.10413872 | G101: =G99/G100 -> 0.11906691 | H101: =H99/H100 -> 0.15383213 | I101: =I99/I100 -> 0.10815995
C103: =C98 -> 43555 | D103: =D98 -> 43921 | E103: =E98 -> 44286 | F103: =F98 -> 44651 | G103: =G98 -> 45016 | H103: =H98 -> 45382 | I103: =I98 -> 45747
B104: Revenue | C104: =C100 -> 19240.13 | D104: =D100 -> 20211.25 | E104: =E100 -> 21712.79 | F104: =F100 -> 29101.28 | G104: =G100 -> 34488.59 | H104: =H100 -> 35494.73 | I104: =I100 -> 33905.62
B105: Average Total Assets | C105: =C85 -> 15006.16 | D105: =D85 -> 16193.405 | E105: =E85 -> 18246.655 | F105: =F85 -> 21656.885 | G105: =G85 -> 24368.88 | H105: =H85 -> 27840.05 | I105: =I85 -> 30128.01
B106: Asset Turnover Ratio(B) | C106: =C104/C105 -> 1.2821488 | D106: =D104/D105 -> 1.2481161 | E106: =E104/E105 -> 1.18996 | F106: =F104/F105 -> 1.3437426 | G106: =G104/G105 -> 1.4152719 | H106: =H104/H105 -> 1.2749521 | I106: =I104/I105 -> 1.1253853
B108: Return On Asset(A*B) | C108: =C106*C101 -> 0.143669 | D108: =D106*D101 -> 0.16705381 | E108: =E106*E101 -> 0.17204742 | F108: =F106*F101 -> 0.13993564 | G108: =G106*G101 -> 0.16851205 | H108: =H106*H101 -> 0.1961286 | I108: =I106*I101 -> 0.12172161

Sheet HistoricalFS
B2: ="Historical Financial Statement - "&'Data Sheet'!B1 -> Historical Financial Statement - ASIAN PAINTS LTD
B3: Years | C3: ='Data Sheet'!B16 -> 42460 | D3: ='Data Sheet'!C16 -> 42825 | E3: ='Data Sheet'!D16 -> 43190 | F3: ='Data Sheet'!E16 -> 43555 | G3: ='Data Sheet'!F16 -> 43921 | H3: ='Data Sheet'!G16 -> 44286 | I3: ='Data Sheet'!H16 -> 44651 | J3: ='Data Sheet'!I16 -> 45016 | ... L3: ='Data Sheet'!K16 -> 45747 | M3: LTM
A5: # | B5: Income Statement
B6: Sales | C6: =IFERROR('Data Sheet'!B17,0) -> 14271.49 | D6: =IFERROR('Data Sheet'!C17,0) -> 15061.99 | E6: =IFERROR('Data Sheet'!D17,0) -> 16824.55 | F6: =IFERROR('Data Sheet'!E17,0) -> 19240.13 | G6: =IFERROR('Data Sheet'!F17,0) -> 20211.25 | H6: =IFERROR('Data Sheet'!G17,0) -> 21712.79 | I6: =IFERROR('Data Sheet'!H17,0) -> 29101.28 | J6: =IFERROR('Data Sheet'!I17,0) -> 34488.59 | ... L6: =IFERROR('Data Sheet'!K17,0) -> 33905.62 | M6: =IFERROR(SUM('Data Sheet'!H42:K42),0) -> 34695.75
B7: Sales Growth | C7: - | D7: =D6/C6-1 -> 0.055390152 | E7: =E6/D6-1 -> 0.11702039 | F7: =F6/E6-1 -> 0.14357472 | G7: =G6/F6-1 -> 0.050473671 | H7: =H6/G6-1 -> 0.074292288 | I7: =I6/H6-1 -> 0.34028285 | J7: =J6/I6-1 -> 0.18512278 | K7: =K6/J6-1 -> 0.029173127 | ... M7: =M6/L6-1 -> 0.023303806
B9: COGS | C9: =IFERROR(SUM('Data Sheet'!B18,'Data Sheet'!B20:B22)-1*'Data Sheet'!B19,0) -> 9413.84 | D9: =IFERROR(SUM('Data Sheet'!C18,'Data Sheet'!C20:C22)-1*'Data Sheet'!C19,0) -> 9732.66 | E9: =IFERROR(SUM('Data Sheet'!D18,'Data Sheet'!D20:D22)-1*'Data Sheet'!D19,0) -> 11194.17 | F9: =IFERROR(SUM('Data Sheet'!E18,'Data Sheet'!E20:E22)-1*'Data Sheet'!E19,0) -> 12905.81 | G9: =IFERROR(SUM('Data Sheet'!F18,'Data Sheet'!F20:F22)-1*'Data Sheet'!F19,0) -> 13158.02 | H9: =IFERROR(SUM('Data Sheet'!G18,'Data Sheet'!G20:G22)-1*'Data Sheet'!G19,0) -> 14035.07 | I9: =IFERROR(SUM('Data Sheet'!H18,'Data Sheet'!H20:H22)-1*'Data Sheet'!H19,0) -> 20590.57 | J9: =IFERROR(SUM('Data Sheet'!I18,'Data Sheet'!I20:I22)-1*'Data Sheet'!I19,0) -> 23766.7 | ... L9: =IFERROR(SUM('Data Sheet'!K18,'Data Sheet'!K20:K22)-1*'Data Sheet'!K19,0) -> 22741.27 | M9: =IFERROR(SUM('Data Sheet'!H43:K43),0) -> 28350.24
B10: COGS % Sales | C10: =C9/C6 -> 0.65962559 | D10: =D9/D6 -> 0.64617358 | E10: =E9/E6 -> 0.66534736 | F10: =F9/F6 -> 0.67077561 | G10: =G9/G6 -> 0.65102455 | H10: =H9/H6 -> 0.64639643 | I10: =I9/I6 -> 0.7075486 | J10: =J9/J6 -> 0.68911776 | ... M10: =M9/M6 -> 0.81710988
B12: Gross Profit | C12: =C6-C9 -> 4857.65 | D12: =D6-D9 -> 5329.33 | E12: =E6-E9 -> 5630.38 | F12: =F6-F9 -> 6334.32 | G12: =G6-G9 -> 7053.23 | H12: =H6-H9 -> 7677.72 | I12: =I6-I9 -> 8510.71 | J12: =J6-J9 -> 10721.89 | ... M12: =M6-M9 -> 6345.51
B13: Gross Margins | C13: =C12/C6 -> 0.34037441 | D13: =D12/D6 -> 0.35382642 | E13: =E12/E6 -> 0.33465264 | F13: =F12/F6 -> 0.32922439 | G13: =G12/G6 -> 0.34897545 | H13: =H12/H6 -> 0.35360357 | I13: =I12/I6 -> 0.2924514 | J13: =J12/J6 -> 0.31088224 | ... M13: =M12/M6 -> 0.18289012
B15: Selling & General Expenses | C15: =IFERROR(SUM('Data Sheet'!B23:B24),0) -> 2132.61 | D15: =IFERROR(SUM('Data Sheet'!C23:C24),0) -> 2335.57 | E15: =IFERROR(SUM('Data Sheet'!D23:D24),0) -> 2426.37 | F15: =IFERROR(SUM('Data Sheet'!E23:E24),0) -> 2569.38 | G15: =IFERROR(SUM('Data Sheet'!F23:F24),0) -> 2891.46 | H15: =IFERROR(SUM('Data Sheet'!G23:G24),0) -> 2822.12 | I15: =IFERROR(SUM('Data Sheet'!H23:H24),0) -> 3707.1 | J15: =IFERROR(SUM('Data Sheet'!I23:I24),0) -> 4462.05 | ... L15: =IFERROR(SUM('Data Sheet'!K23:K24),0) -> 5158.14
B16: S&G Exp % Sales | C16: =C15/C6 -> 0.14943149 | D16: =D15/D6 -> 0.15506384 | E16: =E15/E6 -> 0.14421604 | F16: =F15/F6 -> 0.13354276 | G16: =G15/G6 -> 0.14306191 | H16: =H15/H6 -> 0.12997501 | I16: =I15/I6 -> 0.12738615 | J16: =J15/J6 -> 0.12937757 | ... M16: =M15/M6 -> 0
B18: EBITDA | C18: =C12-C15 -> 2725.04 | D18: =D12-D15 -> 2993.76 | E18: =E12-E15 -> 3204.01 | F18: =F12-F15 -> 3764.94 | G18: =G12-G15 -> 4161.77 | H18: =H12-H15 -> 4855.6 | I18: =I12-I15 -> 4803.61 | J18: =J12-J15 -> 6259.84 | ... L18: =L12-L15 -> 6006.21 | M18: =IFERROR(SUM('Data Sheet'!H51:K51),0) -> 6755.97
B19: EBITDA Margins | C19: =C18/C6 -> 0.19094292 | D19: =D18/D6 -> 0.19876258 | E19: =E18/E6 -> 0.19043659 | F19: =F18/F6 -> 0.19568163 | G19: =G18/G6 -> 0.20591354 | H19: =H18/H6 -> 0.22362856 | I19: =I18/I6 -> 0.16506525 | J19: =J18/J6 -> 0.18150467 | ... M19: =M18/M6 -> 0.19472039
B21: Interest | C21: =IFERROR('Data Sheet'!B27,0) -> 49 | D21: =IFERROR('Data Sheet'!C27,0) -> 37.33 | E21: =IFERROR('Data Sheet'!D27,0) -> 41.47 | F21: =IFERROR('Data Sheet'!E27,0) -> 110.47 | G21: =IFERROR('Data Sheet'!F27,0) -> 102.33 | H21: =IFERROR('Data Sheet'!G27,0) -> 91.63 | I21: =IFERROR('Data Sheet'!H27,0) -> 95.41 | J21: =IFERROR('Data Sheet'!I27,0) -> 144.45 | ... L21: =IFERROR('Data Sheet'!K27,0) -> 227.02 | M21: =IFERROR(SUM('Data Sheet'!H46:K46),0) -> 189.1
B22: Interest % Sales | C22: =C21/C6 -> 0.0034334187 | D22: =D21/D6 -> 0.0024784242 | E22: =E21/E6 -> 0.0024648505 | F22: =F21/F6 -> 0.0057416452 | G22: =G21/G6 -> 0.0050630218 | H22: =H21/H6 -> 0.0042200933 | I22: =I21/I6 -> 0.0032785499 | J22: =J21/J6 -> 0.0041883417 | ... M22: =M21/M6 -> 0.0054502353
B24: Depreciation | C24: =IFERROR('Data Sheet'!B26,0) -> 275.58 | D24: =IFERROR('Data Sheet'!C26,0) -> 334.79 | E24: =IFERROR('Data Sheet'!D26,0) -> 360.47 | F24: =IFERROR('Data Sheet'!E26,0) -> 622.14 | G24: =IFERROR('Data Sheet'!F26,0) -> 780.5 | H24: =IFERROR('Data Sheet'!G26,0) -> 791.27 | I24: =IFERROR('Data Sheet'!H26,0) -> 816.36 | J24: =IFERROR('Data Sheet'!I26,0) -> 858.02 | ... L24: =IFERROR('Data Sheet'!K26,0) -> 1026.34 | M24: =IFERROR(SUM('Data Sheet'!H45:K45),0) -> 1219.97
B25: Depreciation%Sales | C25: =C24/C6 -> 0.019309827 | D25: =D24/D6 -> 0.022227475 | E25: =E24/E6 -> 0.021425239 | F25: =F24/F6 -> 0.03233554 | G25: =G24/G6 -> 0.038617107 | H25: =H24/H6 -> 0.036442576 | I25: =I24/I6 -> 0.028052374 | J25: =J24/J6 -> 0.024878373 | ... M25: =M24/M6 -> 0.035161943
B27: Earnings Before Tax | C27: =IFERROR(C18-SUM(C24,C21),0) -> 2400.46 | D27: =IFERROR(D18-SUM(D24,D21),0) -> 2621.64 | E27: =IFERROR(E18-SUM(E24,E21),0) -> 2802.07 | F27: =IFERROR(F18-SUM(F24,F21),0) -> 3032.33 | G27: =IFERROR(G18-SUM(G24,G21),0) -> 3278.94 | H27: =IFERROR(H18-SUM(H24,H21),0) -> 3972.7 | I27: =IFERROR(I18-SUM(I24,I21),0) -> 3891.84 | J27: =IFERROR(J18-SUM(J24,J21),0) -> 5257.37 | ... M27: =IFERROR(M18-SUM(M24,M21),0) -> 5346.9
B28: EBT % Sales | C28: =C27/C6 -> 0.16819968 | D28: =D27/D6 -> 0.17405668 | E28: =E27/E6 -> 0.1665465 | F28: =F27/F6 -> 0.15760444 | G28: =G27/G6 -> 0.16223341 | H28: =H27/H6 -> 0.18296589 | I28: =I27/I6 -> 0.13373432 | J28: =J27/J6 -> 0.15243795 | ... M28: =M27/M6 -> 0.15410821
B30: Tax | C30: =IFERROR('Data Sheet'!B29,0) -> 844.49 | D30: =IFERROR('Data Sheet'!C29,0) -> 943.29 | E30: =IFERROR('Data Sheet'!D29,0) -> 1040.96 | F30: =IFERROR('Data Sheet'!E29,0) -> 1098.06 | G30: =IFERROR('Data Sheet'!F29,0) -> 854.85 | H30: =IFERROR('Data Sheet'!G29,0) -> 1097.6 | I30: =IFERROR('Data Sheet'!H29,0) -> 1102.91 | J30: =IFERROR('Data Sheet'!I29,0) -> 1493.5 | ... L30: =IFERROR('Data Sheet'!K29,0) -> 1393.36 | M30: =IFERROR(SUM('Data Sheet'!H48:K48),0) -> 1501.54
B31: Effective Tax Rate | C31: =C30/C27 -> 0.3518034 | D31: =D30/D27 -> 0.35980913 | E31: =E30/E27 -> 0.37149679 | F31: =F30/F27 -> 0.36211758 | G31: =G30/G27 -> 0.26070925 | H31: =H30/H27 -> 0.27628565 | I31: =I30/I27 -> 0.28339038 | J31: =J30/J27 -> 0.2840774 | ... M31: =M30/M27 -> 0.2808244
B33: Net Profit | C33: =IFERROR(C27-C30,0) -> 1555.97 | D33: =IFERROR(D27-D30,0) -> 1678.35 | E33: =IFERROR(E27-E30,0) -> 1761.11 | F33: =IFERROR(F27-F30,0) -> 1934.27 | G33: =IFERROR(G27-G30,0) -> 2424.09 | H33: =IFERROR(H27-H30,0) -> 2875.1 | I33: =IFERROR(I27-I30,0) -> 2788.93 | J33: =IFERROR(J27-J30,0) -> 3763.87 | ... M33: =IFERROR(M27-M30,0) -> 3845.36
B34: Net Margins | C34: =C33/C6 -> 0.10902646 | D34: =D33/D6 -> 0.1114295 | E34: =E33/E6 -> 0.10467501 | F34: =F33/F6 -> 0.1005331 | G34: =G33/G6 -> 0.11993766 | H34: =H33/H6 -> 0.13241504 | I34: =I33/I6 -> 0.095835303 | J34: =J33/J6 -> 0.10913377 | ... M34: =M33/M6 -> 0.11083087
B36: No of Equity Shares | C36: =IFERROR('Data Sheet'!B93,0) -> 95.92 | D36: =IFERROR('Data Sheet'!C93,0) -> 95.92 | E36: =IFERROR('Data Sheet'!D93,0) -> 95.92 | F36: =IFERROR('Data Sheet'!E93,0) -> 95.92 | G36: =IFERROR('Data Sheet'!F93,0) -> 95.92 | H36: =IFERROR('Data Sheet'!G93,0) -> 95.92 | I36: =IFERROR('Data Sheet'!H93,0) -> 95.92 | J36: =IFERROR('Data Sheet'!I93,0) -> 95.92 | ... L36: =IFERROR('Data Sheet'!K93,0) -> 95.92 | M36: =L36 -> 95.92
B38: Earnings per Share | C38: =IFERROR(C33/C36,0) -> 16.221539 | D38: =IFERROR(D33/D36,0) -> 17.497394 | E38: =IFERROR(E33/E36,0) -> 18.360196 | F38: =IFERROR(F33/F36,0) -> 20.16545 | G38: =IFERROR(G33/G36,0) -> 25.271997 | H38: =IFERROR(H33/H36,0) -> 29.973937 | I38: =IFERROR(I33/I36,0) -> 29.075584 | J38: =IFERROR(J33/J36,0) -> 39.239679 | ... M38: =IFERROR(M33/M36,0) -> 40.089241
B39: EPS Growth % | D39: =IFERROR(D38/C38-1,0) -> 0.078651902 | E39: =IFERROR(E38/D38-1,0) -> 0.049310335 | F39: =IFERROR(F38/E38-1,0) -> 0.098324352 | G39: =IFERROR(G38/F38-1,0) -> 0.25323249 | H39: =IFERROR(H38/G38-1,0) -> 0.18605332 | I39: =IFERROR(I38/H38-1,0) -> -0.029971131 | J39: =IFERROR(J38/I38-1,0) -> 0.34957493 | K39: =IFERROR(K38/J38-1,0) -> 0.25847333 | ... M39: =IFERROR(M38/L38-1,0) -> 0.14462612
B41: Dividend per Share | C41: =IFERROR('Data Sheet'!B31/HistoricalFS!C36,0) -> 7.5 | D41: =IFERROR('Data Sheet'!C31/HistoricalFS!D36,0) -> 10.300042 | E41: =IFERROR('Data Sheet'!D31/HistoricalFS!E36,0) -> 8.6999583 | F41: =IFERROR('Data Sheet'!E31/HistoricalFS!F36,0) -> 10.5 | G41: =IFERROR('Data Sheet'!F31/HistoricalFS!G36,0) -> 12 | H41: =IFERROR('Data Sheet'!G31/HistoricalFS!H36,0) -> 17.849979 | I41: =IFERROR('Data Sheet'!H31/HistoricalFS!I36,0) -> 19.150021 | J41: =IFERROR('Data Sheet'!I31/HistoricalFS!J36,0) -> 25.650021 | ... M41: =IFERROR('Data Sheet'!L31/HistoricalFS!M36,0) -> 0
B42: Dividend payout ratio | C42: =IFERROR(C41/C38,0) -> 0.46234825 | D42: =IFERROR(D41/D38,0) -> 0.58866148 | E42: =IFERROR(E41/E38,0) -> 0.47384888 | F42: =IFERROR(F41/F38,0) -> 0.52069256 | G42: =IFERROR(G41/G38,0) -> 0.47483386 | H42: =IFERROR(H41/H38,0) -> 0.59551668 | I42: =IFERROR(I41/I38,0) -> 0.65862894 | J42: =IFERROR(J41/J38,0) -> 0.65367561 | ... M42: =IFERROR(M41/M38,0) -> 0
B44: Retained Earnings | C44: =IFERROR(IF(C38>C41,1-C42,0),0) -> 0.53765175 | D44: =IFERROR(IF(D38>D41,1-D42,0),0) -> 0.41133852 | E44: =IFERROR(IF(E38>E41,1-E42,0),0) -> 0.52615112 | F44: =IFERROR(IF(F38>F41,1-F42,0),0) -> 0.47930744 | G44: =IFERROR(IF(G38>G41,1-G42,0),0) -> 0.52516614 | H44: =IFERROR(IF(H38>H41,1-H42,0),0) -> 0.40448332 | I44: =IFERROR(IF(I38>I41,1-I42,0),0) -> 0.34137106 | J44: =IFERROR(IF(J38>J41,1-J42,0),0) -> 0.34632439 | ... M44: =IFERROR(IF(M38>M41,1-M42,0),0) -> 1
A46: # | B46: Balance Sheet
B47: Equity Share Capital | C47: =IFERROR('Data Sheet'!B57,0) -> 95.92 | D47: =IFERROR('Data Sheet'!C57,0) -> 95.92 | E47: =IFERROR('Data Sheet'!D57,0) -> 95.92 | F47: =IFERROR('Data Sheet'!E57,0) -> 95.92 | G47: =IFERROR('Data Sheet'!F57,0) -> 95.92 | H47: =IFERROR('Data Sheet'!G57,0) -> 95.92 | I47: =IFERROR('Data Sheet'!H57,0) -> 95.92 | J47: =IFERROR('Data Sheet'!I57,0) -> 95.92 | ... L47: =IFERROR('Data Sheet'!K57,0) -> 95.92
B48: Reserves | C48: =IFERROR('Data Sheet'!B58,0) -> 6428.9 | D48: =IFERROR('Data Sheet'!C58,0) -> 7507.97 | E48: =IFERROR('Data Sheet'!D58,0) -> 8314.31 | F48: =IFERROR('Data Sheet'!E58,0) -> 9374.63 | G48: =IFERROR('Data Sheet'!F58,0) -> 10034.24 | H48: =IFERROR('Data Sheet'!G58,0) -> 12710.37 | I48: =IFERROR('Data Sheet'!H58,0) -> 13715.64 | J48: =IFERROR('Data Sheet'!I58,0) -> 15896.31 | ... L48: =IFERROR('Data Sheet'!K58,0) -> 19303.89
B49: Borrowings | C49: =IFERROR('Data Sheet'!B59,0) -> 323.29 | D49: =IFERROR('Data Sheet'!C59,0) -> 560.34 | E49: =IFERROR('Data Sheet'!D59,0) -> 533.43 | F49: =IFERROR('Data Sheet'!E59,0) -> 1319.6 | G49: =IFERROR('Data Sheet'!F59,0) -> 1118.5 | H49: =IFERROR('Data Sheet'!G59,0) -> 1093.12 | I49: =IFERROR('Data Sheet'!H59,0) -> 1586.88 | J49: =IFERROR('Data Sheet'!I59,0) -> 1932.62 | ... L49: =IFERROR('Data Sheet'!K59,0) -> 2290.29
B50: Other Liabilities | C50: =IFERROR('Data Sheet'!B60,0) -> 3710.92 | D50: =IFERROR('Data Sheet'!C60,0) -> 4240.96 | E50: =IFERROR('Data Sheet'!D60,0) -> 4819.82 | F50: =IFERROR('Data Sheet'!E60,0) -> 5458.69 | G50: =IFERROR('Data Sheet'!F60,0) -> 4889.31 | H50: =IFERROR('Data Sheet'!G60,0) -> 6455.93 | I50: =IFERROR('Data Sheet'!H60,0) -> 7559.99 | J50: =IFERROR('Data Sheet'!I60,0) -> 7854.48 | ... L50: =IFERROR('Data Sheet'!K60,0) -> 8665.15
B51: Total Liabilities | C51: =IFERROR('Data Sheet'!B61,0) -> 10559.03 | D51: =IFERROR('Data Sheet'!C61,0) -> 12405.19 | E51: =IFERROR('Data Sheet'!D61,0) -> 13763.48 | F51: =IFERROR('Data Sheet'!E61,0) -> 16248.84 | G51: =IFERROR('Data Sheet'!F61,0) -> 16137.97 | H51: =IFERROR('Data Sheet'!G61,0) -> 20355.34 | I51: =IFERROR('Data Sheet'!H61,0) -> 22958.43 | J51: =IFERROR('Data Sheet'!I61,0) -> 25779.33 | ... L51: =IFERROR('Data Sheet'!K61,0) -> 30355.25
B53: Fixed Assets Net Block | C53: =IFERROR('Data Sheet'!B62,0) -> 3416.35 | D53: =IFERROR('Data Sheet'!C62,0) -> 3303.74 | E53: =IFERROR('Data Sheet'!D62,0) -> 3732.24 | F53: =IFERROR('Data Sheet'!E62,0) -> 6496.56 | G53: =IFERROR('Data Sheet'!F62,0) -> 6272.31 | H53: =IFERROR('Data Sheet'!G62,0) -> 5858.52 | I53: =IFERROR('Data Sheet'!H62,0) -> 5519.06 | J53: =IFERROR('Data Sheet'!I62,0) -> 5770.46 | ... L53: =IFERROR('Data Sheet'!K62,0) -> 9220.1
B54: Capital Work in Progress | C54: =IFERROR('Data Sheet'!B63,0) -> 106.59 | D54: =IFERROR('Data Sheet'!C63,0) -> 257.54 | E54: =IFERROR('Data Sheet'!D63,0) -> 1405.11 | F54: =IFERROR('Data Sheet'!E63,0) -> 209.67 | G54: =IFERROR('Data Sheet'!F63,0) -> 140.24 | H54: =IFERROR('Data Sheet'!G63,0) -> 182.98 | I54: =IFERROR('Data Sheet'!H63,0) -> 426.43 | J54: =IFERROR('Data Sheet'!I63,0) -> 1019.59 | ... L54: =IFERROR('Data Sheet'!K63,0) -> 1254.49
B55: Investments | C55: =IFERROR('Data Sheet'!B64,0) -> 2712.13 | D55: =IFERROR('Data Sheet'!C64,0) -> 2651.99 | E55: =IFERROR('Data Sheet'!D64,0) -> 2140.7 | F55: =IFERROR('Data Sheet'!E64,0) -> 2568.58 | G55: =IFERROR('Data Sheet'!F64,0) -> 2018.85 | H55: =IFERROR('Data Sheet'!G64,0) -> 4736.8 | I55: =IFERROR('Data Sheet'!H64,0) -> 3247.53 | J55: =IFERROR('Data Sheet'!I64,0) -> 4261.71 | ... L55: =IFERROR('Data Sheet'!K64,0) -> 4724.75
B56: Other Assets | C56: =IFERROR('Data Sheet'!B65-SUM('Data Sheet'!B67:B69),0) -> 714.68 | D56: =IFERROR('Data Sheet'!C65-SUM('Data Sheet'!C67:C69),0) -> 1317.17 | E56: =IFERROR('Data Sheet'!D65-SUM('Data Sheet'!D67:D69),0) -> 1691.84 | F56: =IFERROR('Data Sheet'!E65-SUM('Data Sheet'!E67:E69),0) -> 1471.96 | G56: =IFERROR('Data Sheet'!F65-SUM('Data Sheet'!F67:F69),0) -> 1738.71 | H56: =IFERROR('Data Sheet'!G65-SUM('Data Sheet'!G67:G69),0) -> 2565.52 | I56: =IFERROR('Data Sheet'!H65-SUM('Data Sheet'!H67:H69),0) -> 2876.66 | J56: =IFERROR('Data Sheet'!I65-SUM('Data Sheet'!I67:I69),0) -> 3036.17 | ... L56: =IFERROR('Data Sheet'!K65-SUM('Data Sheet'!K67:K69),0) -> 3341.01
B57: Total Non Current Assets | C57: =SUM(C53:C56) -> 6949.75 | D57: =SUM(D53:D56) -> 7530.44 | E57: =SUM(E53:E56) -> 8969.89 | F57: =SUM(F53:F56) -> 10746.77 | G57: =SUM(G53:G56) -> 10170.11 | H57: =SUM(H53:H56) -> 13343.82 | I57: =SUM(I53:I56) -> 12069.68 | J57: =SUM(J53:J56) -> 14087.93 | ... L57: =SUM(L53:L56) -> 18540.35
B59: Receivables | C59: =IFERROR('Data Sheet'!B67,0) -> 1186.84 | D59: =IFERROR('Data Sheet'!C67,0) -> 1446.6 | E59: =IFERROR('Data Sheet'!D67,0) -> 1730.63 | F59: =IFERROR('Data Sheet'!E67,0) -> 1907.33 | G59: =IFERROR('Data Sheet'!F67,0) -> 1795.22 | H59: =IFERROR('Data Sheet'!G67,0) -> 2602.17 | I59: =IFERROR('Data Sheet'!H67,0) -> 3871.44 | J59: =IFERROR('Data Sheet'!I67,0) -> 4636.94 | ... L59: =IFERROR('Data Sheet'!K67,0) -> 4313.65
B60: Inventory | C60: =IFERROR('Data Sheet'!B68,0) -> 1998.24 | D60: =IFERROR('Data Sheet'!C68,0) -> 2626.94 | E60: =IFERROR('Data Sheet'!D68,0) -> 2658.31 | F60: =IFERROR('Data Sheet'!E68,0) -> 3149.86 | G60: =IFERROR('Data Sheet'!F68,0) -> 3389.81 | H60: =IFERROR('Data Sheet'!G68,0) -> 3798.6 | I60: =IFERROR('Data Sheet'!H68,0) -> 6152.98 | J60: =IFERROR('Data Sheet'!I68,0) -> 6210.64 | ... L60: =IFERROR('Data Sheet'!K68,0) -> 6719.27
B61: Cash & Bank | C61: =IFERROR('Data Sheet'!B69,0) -> 424.2 | D61: =IFERROR('Data Sheet'!C69,0) -> 801.21 | E61: =IFERROR('Data Sheet'!D69,0) -> 404.65 | F61: =IFERROR('Data Sheet'!E69,0) -> 444.88 | G61: =IFERROR('Data Sheet'!F69,0) -> 782.83 | H61: =IFERROR('Data Sheet'!G69,0) -> 610.75 | I61: =IFERROR('Data Sheet'!H69,0) -> 864.33 | J61: =IFERROR('Data Sheet'!I69,0) -> 843.82 | ... L61: =IFERROR('Data Sheet'!K69,0) -> 781.98
B62: Total Current Assets | C62: =IFERROR(SUM(C59:C61),0) -> 3609.28 | D62: =IFERROR(SUM(D59:D61),0) -> 4874.75 | E62: =IFERROR(SUM(E59:E61),0) -> 4793.59 | F62: =IFERROR(SUM(F59:F61),0) -> 5502.07 | G62: =IFERROR(SUM(G59:G61),0) -> 5967.86 | H62: =IFERROR(SUM(H59:H61),0) -> 7011.52 | I62: =IFERROR(SUM(I59:I61),0) -> 10888.75 | J62: =IFERROR(SUM(J59:J61),0) -> 11691.4 | ... L62: =IFERROR(SUM(L59:L61),0) -> 11814.9
B64: Total Assets | C64: =IFERROR(C62+C57,0) -> 10559.03 | D64: =IFERROR(D62+D57,0) -> 12405.19 | E64: =IFERROR(E62+E57,0) -> 13763.48 | F64: =IFERROR(F62+F57,0) -> 16248.84 | G64: =IFERROR(G62+G57,0) -> 16137.97 | H64: =IFERROR(H62+H57,0) -> 20355.34 | I64: =IFERROR(I62+I57,0) -> 22958.43 | J64: =IFERROR(J62+J57,0) -> 25779.33 | ... L64: =IFERROR(L62+L57,0) -> 30355.25
B66: Check | C66: =C64=C51 -> TRUE | D66: =D64=D51 -> TRUE | E66: =E64=E51 -> TRUE | F66: =F64=F51 -> TRUE | G66: =G64=G51 -> TRUE | H66: =H64=H51 -> TRUE | I66: =I64=I51 -> TRUE | J66: =J64=J51 -> TRUE | ... L66: =L64=L51 -> TRUE
A68: # | B68: Cash Flow Statements
B70: Cash from Operating Activities | C70: ='Data Sheet'!B82 -> 2242.95 | D70: ='Data Sheet'!C82 -> 1527.33 | E70: ='Data Sheet'!D82 -> 2113.44 | F70: ='Data Sheet'!E82 -> 2469.54 | G70: ='Data Sheet'!F82 -> 3038.15 | H70: ='Data Sheet'!G82 -> 3683.35 | I70: ='Data Sheet'!H82 -> 986.49 | J70: ='Data Sheet'!I82 -> 4193.43 | ... L70: ='Data Sheet'!K82 -> 4423.96
B72: Cash from Investing Activities | C72: ='Data Sheet'!B83 -> -866.21 | D72: ='Data Sheet'!C83 -> -681.11 | E72: ='Data Sheet'!D83 -> -1556.14 | F72: ='Data Sheet'!E83 -> -917.79 | G72: ='Data Sheet'!F83 -> -517.91 | H72: ='Data Sheet'!G83 -> -540.54 | I72: ='Data Sheet'!H83 -> -316.75 | J72: ='Data Sheet'!I83 -> -1282.34 | ... L72: ='Data Sheet'!K83 -> -940.91
B74: Cash from Financing Activities | C74: ='Data Sheet'!B84 -> -848.98 | D74: ='Data Sheet'!C84 -> -756.43 | E74: ='Data Sheet'!D84 -> -1379.14 | F74: ='Data Sheet'!E84 -> -1117.46 | G74: ='Data Sheet'!F84 -> -2871.46 | H74: ='Data Sheet'!G84 -> -650.4 | I74: ='Data Sheet'!H84 -> -1807.61 | J74: ='Data Sheet'!I84 -> -2140.05 | ... L74: ='Data Sheet'!K84 -> -3752.58
B76: Net Cash Flow | C76: =IFERROR(C70+C72+C74,0) -> 527.76 | D76: =IFERROR(D70+D72+D74,0) -> 89.79 | E76: =IFERROR(E70+E72+E74,0) -> -821.84 | F76: =IFERROR(F70+F72+F74,0) -> 434.29 | G76: =IFERROR(G70+G72+G74,0) -> -351.22 | H76: =IFERROR(H70+H72+H74,0) -> 2492.41 | I76: =IFERROR(I70+I72+I74,0) -> -1137.87 | J76: =IFERROR(J70+J72+J74,0) -> 771.04 | ... L76: =IFERROR(L70+L72+L74,0) -> -269.53

Sheet Raw FS
B2: Particulars | C2: =IFERROR('Data Sheet 2'!C2,0) -> 41699 | D2: =IFERROR('Data Sheet 2'!D2,0) -> 42064 | E2: =IFERROR('Data Sheet 2'!E2,0) -> 42430 | F2: =IFERROR('Data Sheet 2'!F2,0) -> 42795 | G2: =IFERROR('Data Sheet 2'!G2,0) -> 43160 | H2: =IFERROR('Data Sheet 2'!H2,0) -> 43525 | I2: =IFERROR('Data Sheet 2'!I2,0) -> 43891 | J2: =IFERROR('Data Sheet 2'!J2,0) -> 44256 | ... N2: =IFERROR('Data Sheet 2'!N2,0) -> 45717
B4: Equity Capital | C4: =IFERROR('Data Sheet 2'!C3,0) -> 96 | D4: =IFERROR('Data Sheet 2'!D3,0) -> 96 | E4: =IFERROR('Data Sheet 2'!E3,0) -> 96 | F4: =IFERROR('Data Sheet 2'!F3,0) -> 96 | G4: =IFERROR('Data Sheet 2'!G3,0) -> 96 | H4: =IFERROR('Data Sheet 2'!H3,0) -> 96 | I4: =IFERROR('Data Sheet 2'!I3,0) -> 96 | J4: =IFERROR('Data Sheet 2'!J3,0) -> 96 | ... N4: =IFERROR('Data Sheet 2'!N3,0) -> 96
B5: Reserves | C5: =IFERROR('Data Sheet 2'!C4,0) -> 3943 | D5: =IFERROR('Data Sheet 2'!D4,0) -> 4646 | E5: =IFERROR('Data Sheet 2'!E4,0) -> 6429 | F5: =IFERROR('Data Sheet 2'!F4,0) -> 7508 | G5: =IFERROR('Data Sheet 2'!G4,0) -> 8314 | H5: =IFERROR('Data Sheet 2'!H4,0) -> 9375 | I5: =IFERROR('Data Sheet 2'!I4,0) -> 10034 | J5: =IFERROR('Data Sheet 2'!J4,0) -> 12710 | ... N5: =IFERROR('Data Sheet 2'!N4,0) -> 19304
B6: Borrowings -
B7: Long term Borrowings | C7: =IFERROR('Data Sheet 2'!C6,0) -> 41 | D7: =IFERROR('Data Sheet 2'!D6,0) -> 78 | E7: =IFERROR('Data Sheet 2'!E6,0) -> 73 | F7: =IFERROR('Data Sheet 2'!F6,0) -> 41 | G7: =IFERROR('Data Sheet 2'!G6,0) -> 28 | H7: =IFERROR('Data Sheet 2'!H6,0) -> 19 | I7: =IFERROR('Data Sheet 2'!I6,0) -> 19 | J7: =IFERROR('Data Sheet 2'!J6,0) -> 15 | ... N7: =IFERROR('Data Sheet 2'!N6,0) -> 260
B8: Short term Borrowings | C8: =IFERROR('Data Sheet 2'!C7,0) -> 199 | D8: =IFERROR('Data Sheet 2'!D7,0) -> 332 | E8: =IFERROR('Data Sheet 2'!E7,0) -> 231 | F8: =IFERROR('Data Sheet 2'!F7,0) -> 504 | G8: =IFERROR('Data Sheet 2'!G7,0) -> 492 | H8: =IFERROR('Data Sheet 2'!H7,0) -> 597 | I8: =IFERROR('Data Sheet 2'!I7,0) -> 321 | J8: =IFERROR('Data Sheet 2'!J7,0) -> 334 | ... N8: =IFERROR('Data Sheet 2'!N7,0) -> 604
B9: Lease Liabilities | C9: =IFERROR('Data Sheet 2'!C8,0) -> 0 | D9: =IFERROR('Data Sheet 2'!D8,0) -> 0 | E9: =IFERROR('Data Sheet 2'!E8,0) -> 0 | F9: =IFERROR('Data Sheet 2'!F8,0) -> 0 | G9: =IFERROR('Data Sheet 2'!G8,0) -> 0 | H9: =IFERROR('Data Sheet 2'!H8,0) -> 693 | I9: =IFERROR('Data Sheet 2'!I8,0) -> 764 | J9: =IFERROR('Data Sheet 2'!J8,0) -> 745 | ... N9: =IFERROR('Data Sheet 2'!N8,0) -> 1427
B10: Other Borrowings | C10: =IFERROR('Data Sheet 2'!C9,0) -> 9 | D10: =IFERROR('Data Sheet 2'!D9,0) -> 8 | E10: =IFERROR('Data Sheet 2'!E9,0) -> 20 | F10: =IFERROR('Data Sheet 2'!F9,0) -> 15 | G10: =IFERROR('Data Sheet 2'!G9,0) -> 13 | H10: =IFERROR('Data Sheet 2'!H9,0) -> 11 | I10: =IFERROR('Data Sheet 2'!I9,0) -> 15 | J10: =IFERROR('Data Sheet 2'!J9,0) -> 0 | ... N10: =IFERROR('Data Sheet 2'!N9,0) -> 0
B11: Other Liabilities -
B12: Non controlling int | C12: =IFERROR('Data Sheet 2'!C11,0) -> 246 | D12: =IFERROR('Data Sheet 2'!D11,0) -> 264 | E12: =IFERROR('Data Sheet 2'!E11,0) -> 384 | F12: =IFERROR('Data Sheet 2'!F11,0) -> 375 | G12: =IFERROR('Data Sheet 2'!G11,0) -> 328 | H12: =IFERROR('Data Sheet 2'!H11,0) -> 361 | I12: =IFERROR('Data Sheet 2'!I11,0) -> 404 | J12: =IFERROR('Data Sheet 2'!J11,0) -> 423 | ... N12: =IFERROR('Data Sheet 2'!N11,0) -> 659
B13: Trade Payables | C13: =IFERROR('Data Sheet 2'!C12,0) -> 1746 | D13: =IFERROR('Data Sheet 2'!D12,0) -> 1549 | E13: =IFERROR('Data Sheet 2'!E12,0) -> 1565 | F13: =IFERROR('Data Sheet 2'!F12,0) -> 1923 | G13: =IFERROR('Data Sheet 2'!G12,0) -> 2160 | H13: =IFERROR('Data Sheet 2'!H12,0) -> 2394 | I13: =IFERROR('Data Sheet 2'!I12,0) -> 2137 | J13: =IFERROR('Data Sheet 2'!J12,0) -> 3379 | ... N13: =IFERROR('Data Sheet 2'!N12,0) -> 3848
B14: Advance from Customers | C14: =IFERROR('Data Sheet 2'!C13,0) -> 0 | D14: =IFERROR('Data Sheet 2'!D13,0) -> 5 | E14: =IFERROR('Data Sheet 2'!E13,0) -> 12 | F14: =IFERROR('Data Sheet 2'!F13,0) -> 17 | G14: =IFERROR('Data Sheet 2'!G13,0) -> 16 | H14: =IFERROR('Data Sheet 2'!H13,0) -> 13 | I14: =IFERROR('Data Sheet 2'!I13,0) -> 29 | J14: =IFERROR('Data Sheet 2'!J13,0) -> 41 | ... N14: =IFERROR('Data Sheet 2'!N13,0) -> 173
B15: Other liability items | C15: =IFERROR('Data Sheet 2'!C14,0) -> 1795 | D15: =IFERROR('Data Sheet 2'!D14,0) -> 1937 | E15: =IFERROR('Data Sheet 2'!E14,0) -> 1750 | F15: =IFERROR('Data Sheet 2'!F14,0) -> 1925 | G15: =IFERROR('Data Sheet 2'!G14,0) -> 2316 | H15: =IFERROR('Data Sheet 2'!H14,0) -> 2690 | I15: =IFERROR('Data Sheet 2'!I14,0) -> 2320 | J15: =IFERROR('Data Sheet 2'!J14,0) -> 2613 | ... N15: =IFERROR('Data Sheet 2'!N14,0) -> 3985
B16: Total Liabilities | C16: =SUM(C4:C15) -> 8075 | D16: =SUM(D4:D15) -> 8915 | E16: =SUM(E4:E15) -> 10560 | F16: =SUM(F4:F15) -> 12404 | G16: =SUM(G4:G15) -> 13763 | H16: =SUM(H4:H15) -> 16249 | I16: =SUM(I4:I15) -> 16139 | J16: =SUM(J4:J15) -> 20356 | ... N16: =SUM(N4:N15) -> 30356
B18: Fixed Assets -
B19: Land | C19: =IFERROR('Data Sheet 2'!C17,0) -> 247 | D19: =IFERROR('Data Sheet 2'!D17,0) -> 251 | E19: =IFERROR('Data Sheet 2'!E17,0) -> 429 | F19: =IFERROR('Data Sheet 2'!F17,0) -> 408 | G19: =IFERROR('Data Sheet 2'!G17,0) -> 586 | H19: =IFERROR('Data Sheet 2'!H17,0) -> 605 | I19: =IFERROR('Data Sheet 2'!I17,0) -> 640 | J19: =IFERROR('Data Sheet 2'!J17,0) -> 644 | ... N19: =IFERROR('Data Sheet 2'!N17,0) -> 1050
B20: Building | C20: =IFERROR('Data Sheet 2'!C18,0) -> 931 | D20: =IFERROR('Data Sheet 2'!D18,0) -> 962 | E20: =IFERROR('Data Sheet 2'!E18,0) -> 923 | F20: =IFERROR('Data Sheet 2'!F18,0) -> 931 | G20: =IFERROR('Data Sheet 2'!G18,0) -> 957 | H20: =IFERROR('Data Sheet 2'!H18,0) -> 2402 | I20: =IFERROR('Data Sheet 2'!I18,0) -> 2257 | J20: =IFERROR('Data Sheet 2'!J18,0) -> 2249 | ... N20: =IFERROR('Data Sheet 2'!N18,0) -> 4136
B21: Plant Machinery | C21: =IFERROR('Data Sheet 2'!C19,0) -> 2054 | D21: =IFERROR('Data Sheet 2'!D19,0) -> 2132 | E21: =IFERROR('Data Sheet 2'!E19,0) -> 1793 | F21: =IFERROR('Data Sheet 2'!F19,0) -> 1980 | G21: =IFERROR('Data Sheet 2'!G19,0) -> 2157 | H21: =IFERROR('Data Sheet 2'!H19,0) -> 4006 | I21: =IFERROR('Data Sheet 2'!I19,0) -> 4208 | J21: =IFERROR('Data Sheet 2'!J19,0) -> 4340 | ... N21: =IFERROR('Data Sheet 2'!N19,0) -> 7576
B22: Equipments | C22: =IFERROR('Data Sheet 2'!C20,0) -> 155 | D22: =IFERROR('Data Sheet 2'!D20,0) -> 171 | E22: =IFERROR('Data Sheet 2'!E20,0) -> 97 | F22: =IFERROR('Data Sheet 2'!F20,0) -> 119 | G22: =IFERROR('Data Sheet 2'!G20,0) -> 200 | H22: =IFERROR('Data Sheet 2'!H20,0) -> 221 | I22: =IFERROR('Data Sheet 2'!I20,0) -> 241 | J22: =IFERROR('Data Sheet 2'!J20,0) -> 243 | ... N22: =IFERROR('Data Sheet 2'!N20,0) -> 325
B23: Furniture n fittings | C23: =IFERROR('Data Sheet 2'!C21,0) -> 71 | D23: =IFERROR('Data Sheet 2'!D21,0) -> 83 | E23: =IFERROR('Data Sheet 2'!E21,0) -> 49 | F23: =IFERROR('Data Sheet 2'!F21,0) -> 59 | G23: =IFERROR('Data Sheet 2'!G21,0) -> 72 | H23: =IFERROR('Data Sheet 2'!H21,0) -> 88 | I23: =IFERROR('Data Sheet 2'!I21,0) -> 94 | J23: =IFERROR('Data Sheet 2'!J21,0) -> 99 | ... N23: =IFERROR('Data Sheet 2'!N21,0) -> 203
B24: Vehicles | C24: =IFERROR('Data Sheet 2'!C22,0) -> 14 | D24: =IFERROR('Data Sheet 2'!D22,0) -> 18 | E24: =IFERROR('Data Sheet 2'!E22,0) -> 11 | F24: =IFERROR('Data Sheet 2'!F22,0) -> 14 | G24: =IFERROR('Data Sheet 2'!G22,0) -> 27 | H24: =IFERROR('Data Sheet 2'!H22,0) -> 47 | I24: =IFERROR('Data Sheet 2'!I22,0) -> 43 | J24: =IFERROR('Data Sheet 2'!J22,0) -> 38 | ... N24: =IFERROR('Data Sheet 2'!N22,0) -> 39
B25: Intangible Assets | C25: =IFERROR('Data Sheet 2'!C23,0) -> 203 | D25: =IFERROR('Data Sheet 2'!D23,0) -> 351 | E25: =IFERROR('Data Sheet 2'!E23,0) -> 339 | F25: =IFERROR('Data Sheet 2'!F23,0) -> 276 | G25: =IFERROR('Data Sheet 2'!G23,0) -> 468 | H25: =IFERROR('Data Sheet 2'!H23,0) -> 512 | I25: =IFERROR('Data Sheet 2'!I23,0) -> 505 | J25: =IFERROR('Data Sheet 2'!J23,0) -> 476 | ... N25: =IFERROR('Data Sheet 2'!N23,0) -> 827
B26: Other fixed assets | C26: =IFERROR('Data Sheet 2'!C24,0) -> 128 | D26: =IFERROR('Data Sheet 2'!D24,0) -> 145 | E26: =IFERROR('Data Sheet 2'!E24,0) -> 103 | F26: =IFERROR('Data Sheet 2'!F24,0) -> 128 | G26: =IFERROR('Data Sheet 2'!G24,0) -> 238 | H26: =IFERROR('Data Sheet 2'!H24,0) -> 261 | I26: =IFERROR('Data Sheet 2'!I24,0) -> 293 | J26: =IFERROR('Data Sheet 2'!J24,0) -> 302 | ... N26: =IFERROR('Data Sheet 2'!N24,0) -> 328
B27: Gross Block | C27: =SUM(C19:C26) -> 3803 | D27: =SUM(D19:D26) -> 4113 | E27: =SUM(E19:E26) -> 3744 | F27: =SUM(F19:F26) -> 3915 | G27: =SUM(G19:G26) -> 4705 | H27: =SUM(H19:H26) -> 8142 | I27: =SUM(I19:I26) -> 8281 | J27: =SUM(J19:J26) -> 8391 | ... N27: =SUM(N19:N26) -> 14484
B28: Accumulated Depreciation | C28: =IFERROR('Data Sheet 2'!C26,0) -> 1242 | D28: =IFERROR('Data Sheet 2'!D26,0) -> 1452 | E28: =IFERROR('Data Sheet 2'!E26,0) -> 327 | F28: =IFERROR('Data Sheet 2'!F26,0) -> 610 | G28: =IFERROR('Data Sheet 2'!G26,0) -> 973 | H28: =IFERROR('Data Sheet 2'!H26,0) -> 1644 | I28: =IFERROR('Data Sheet 2'!I26,0) -> 2010 | J28: =IFERROR('Data Sheet 2'!J26,0) -> 2533 | ... N28: =IFERROR('Data Sheet 2'!N26,0) -> 5264
B29: Net Block | C29: =C27-C28 -> 2561 | D29: =D27-D28 -> 2661 | E29: =E27-E28 -> 3417 | F29: =F27-F28 -> 3305 | G29: =G27-G28 -> 3732 | H29: =H27-H28 -> 6498 | I29: =I27-I28 -> 6271 | J29: =J27-J28 -> 5858 | ... N29: =N27-N28 -> 9220
B31: CWIP | C31: =IFERROR('Data Sheet 2'!C27,0) -> 72 | D31: =IFERROR('Data Sheet 2'!D27,0) -> 196 | E31: =IFERROR('Data Sheet 2'!E27,0) -> 107 | F31: =IFERROR('Data Sheet 2'!F27,0) -> 258 | G31: =IFERROR('Data Sheet 2'!G27,0) -> 1405 | H31: =IFERROR('Data Sheet 2'!H27,0) -> 210 | I31: =IFERROR('Data Sheet 2'!I27,0) -> 140 | J31: =IFERROR('Data Sheet 2'!J27,0) -> 183 | ... N31: =IFERROR('Data Sheet 2'!N27,0) -> 1254
B32: Investments | C32: =IFERROR('Data Sheet 2'!C28,0) -> 1424 | D32: =IFERROR('Data Sheet 2'!D28,0) -> 1588 | E32: =IFERROR('Data Sheet 2'!E28,0) -> 2712 | F32: =IFERROR('Data Sheet 2'!F28,0) -> 2652 | G32: =IFERROR('Data Sheet 2'!G28,0) -> 2141 | H32: =IFERROR('Data Sheet 2'!H28,0) -> 2569 | I32: =IFERROR('Data Sheet 2'!I28,0) -> 2019 | J32: =IFERROR('Data Sheet 2'!J28,0) -> 4737 | ... N32: =IFERROR('Data Sheet 2'!N28,0) -> 4725
B34: Other Assets -
B35: Inventories | C35: =IFERROR('Data Sheet 2'!C30,0) -> 2070 | D35: =IFERROR('Data Sheet 2'!D30,0) -> 2259 | E35: =IFERROR('Data Sheet 2'!E30,0) -> 1998 | F35: =IFERROR('Data Sheet 2'!F30,0) -> 2627 | G35: =IFERROR('Data Sheet 2'!G30,0) -> 2658 | H35: =IFERROR('Data Sheet 2'!H30,0) -> 3150 | I35: =IFERROR('Data Sheet 2'!I30,0) -> 3390 | J35: =IFERROR('Data Sheet 2'!J30,0) -> 3799 | ... N35: =IFERROR('Data Sheet 2'!N30,0) -> 6719
B36: Trade receivables | C36: =IFERROR('Data Sheet 2'!C31,0) -> 1110 | D36: =IFERROR('Data Sheet 2'!D31,0) -> 1182 | E36: =IFERROR('Data Sheet 2'!E31,0) -> 1187 | F36: =IFERROR('Data Sheet 2'!F31,0) -> 1447 | G36: =IFERROR('Data Sheet 2'!G31,0) -> 1731 | H36: =IFERROR('Data Sheet 2'!H31,0) -> 1907 | I36: =IFERROR('Data Sheet 2'!I31,0) -> 1795 | J36: =IFERROR('Data Sheet 2'!J31,0) -> 2602 | ... N36: =IFERROR('Data Sheet 2'!N31,0) -> 4314
B37: Cash Equivalents | C37: =IFERROR('Data Sheet 2'!C32,0) -> 229 | D37: =IFERROR('Data Sheet 2'!D32,0) -> 204 | E37: =IFERROR('Data Sheet 2'!E32,0) -> 424 | F37: =IFERROR('Data Sheet 2'!F32,0) -> 801 | G37: =IFERROR('Data Sheet 2'!G32,0) -> 405 | H37: =IFERROR('Data Sheet 2'!H32,0) -> 445 | I37: =IFERROR('Data Sheet 2'!I32,0) -> 783 | J37: =IFERROR('Data Sheet 2'!J32,0) -> 611 | ... N37: =IFERROR('Data Sheet 2'!N32,0) -> 782
B38: Loans n Advances | C38: =IFERROR('Data Sheet 2'!C33,0) -> 7 | D38: =IFERROR('Data Sheet 2'!D33,0) -> 8 | E38: =IFERROR('Data Sheet 2'!E33,0) -> 9 | F38: =IFERROR('Data Sheet 2'!F33,0) -> 14 | G38: =IFERROR('Data Sheet 2'!G33,0) -> 13 | H38: =IFERROR('Data Sheet 2'!H33,0) -> 16 | I38: =IFERROR('Data Sheet 2'!I33,0) -> 12 | J38: =IFERROR('Data Sheet 2'!J33,0) -> 11 | ... N38: =IFERROR('Data Sheet 2'!N33,0) -> 22
B39: Other asset items | C39: =IFERROR('Data Sheet 2'!C34,0) -> 603 | D39: =IFERROR('Data Sheet 2'!D34,0) -> 817 | E39: =IFERROR('Data Sheet 2'!E34,0) -> 705 | F39: =IFERROR('Data Sheet 2'!F34,0) -> 1303 | G39: =IFERROR('Data Sheet 2'!G34,0) -> 1678 | H39: =IFERROR('Data Sheet 2'!H34,0) -> 1456 | I39: =IFERROR('Data Sheet 2'!I34,0) -> 1727 | J39: =IFERROR('Data Sheet 2'!J34,0) -> 2555 | ... N39: =IFERROR('Data Sheet 2'!N34,0) -> 3319
B40: Total Assets | C40: =SUM(C29:C39) -> 8076 | D40: =SUM(D29:D39) -> 8915 | E40: =SUM(E29:E39) -> 10559 | F40: =SUM(F29:F39) -> 12407 | G40: =SUM(G29:G39) -> 13763 | H40: =SUM(H29:H39) -> 16251 | I40: =SUM(I29:I39) -> 16137 | J40: =SUM(J29:J39) -> 20356 | ... N40: =SUM(N29:N39) -> 30355
C43: 41699 | D43: 42064 | E43: 42430 | F43: 42795 | G43: 43160 | H43: 43525 | I43: 43891 | J43: 44256 | K43: 44621 | L43: 44986 | M43: 45352 | N43: 45717
B44: Cash from Operating Activity - | C44: 1402 | D44: 1188 | E44: 2243 | F44: 1527 | G44: 2113 | H44: 2470 | I44: 3038 | J44: 3683 | K44: 986 | L44: 4193 | M44: 6104 | N44: 4424
B45: Profit from operations | C45: 2051 | D45: 2271 | E45: 2848 | F45: 3056 | G45: 3274 | H45: 3861 | I45: 4380 | J45: 4970 | K45: 4957 | L45: 6460 | M45: 7929 | N45: 6390
B46: Receivables | C46: -254 | D46: -155 | E46: -146 | F46: -475 | G46: -483 | H46: -205 | I46: 160 | J46: -849 | K46: -1326 | L46: -834 | M46: -362 | N46: 282
B47: Inventory | C47: -231 | D47: -144 | E47: 202 | F47: -629 | G47: -39 | H47: -492 | I47: -251 | J47: -409 | K47: -2354 | L47: -56 | M47: 315 | N47: -805
B48: Payables | C48: 317 | D48: -151 | E48: 142 | F48: 501 | G48: 442 | H48: 287 | I48: -241 | J48: 1143 | K48: 644 | L48: -539 | M48: 269 | N48: -160
B49: Other WC items | C49: 0 | D49: 0 | E49: 0 | F49: 0 | G49: 0 | H49: 0 | I49: 0 | J49: -92 | K49: 242 | L49: 657 | M49: -212 | N49: 114
B50: Working capital changes | C50: -168 | D50: -450 | E50: 198 | F50: -603 | G50: -80 | H50: -410 | I50: -331 | J50: -206 | K50: -2795 | L50: -772 | M50: 10 | N50: -570
B51: Direct taxes | C51: -480 | D51: -633 | E51: -802 | F51: -925 | G51: -1081 | H51: -982 | I51: -1011 | J51: -1080 | K51: -1176 | L51: -1494 | M51: -1835 | N51: -1396
B52: Exceptional CF items | C52: 0 | D52: 10 | E52: 0 | F52: 0 | G52: 0 | H52: 0 | I52: 0 | J52: 0 | K52: 0 | L52: 0 | M52: 0 | N52: 0
B53: Cash from Investing Activity - | C53: -586 | D53: -465 | E53: -866 | F53: -681 | G53: -1556 | H53: -918 | I53: -518 | J53: -541 | K53: -317 | L53: -1282 | M53: -2548 | N53: -941
B54: Fixed assets purchased | C54: -251 | D54: -454 | E54: -817 | F54: -684 | G54: -1426 | H54: -1151 | I54: -414 | J54: -289 | K54: -551 | L54: -1446 | M54: -2496 | N54: -1830
B55: Fixed assets sold | C55: 16 | D55: 16 | E55: 15 | F55: 17 | G55: 17 | H55: 17 | I55: 37 | J55: 28 | K55: 40 | L55: 26 | M55: 5 | N55: 10
... B70: Net Cash Flow | C70: 190 | D70: 147 | E70: 528 | F70: 90 | G70: -822 | H70: 434 | I70: -351 | J70: 2492 | K70: -1138 | L70: 771 | M70: 573 | N70: -270

Sheet Data Sheet
A1: COMPANY NAME | B1: ASIAN PAINTS LTD | E1: =IF(B2<>B3, "A NEW VERSION OF THE WORKSHEET IS AVAILABLE", "")
A2: LATEST VERSION | B2: 2.1 | E2: PLEASE DO NOT MAKE ANY CHANGES TO THIS SHEET
A3: CURRENT VERSION | B3: 2.1
A5: META
A6: Number of shares | B6: =IF(B9>0, B9/B8, 0) -> 95.91978
A7: Face Value | B7: 1
A8: Current Price | B8: 2605.6
A9: Market Capitalization | B9: 249928.58
A15: PROFIT & LOSS | B15: =B26+B34 -> 3189.81 | K15: =K17-K18-K20-K21-K22-K23-K19 -> 6879.41
A16: Report Date | B16: 42460 | C16: 42825 | D16: 43190 | E16: 43555 | F16: 43921 | G16: 44286 | H16: 44651 | I16: 45016 | J16: 45382 | K16: 45747
A17: Sales | B17: 14271.49 | C17: 15061.99 | D17: 16824.55 | E17: 19240.13 | F17: 20211.25 | G17: 21712.79 | H17: 29101.28 | I17: 34488.59 | J17: 35494.73 | K17: 33905.62
A18: Raw Material Cost | B18: 6569.83 | C18: 7452.6 | D18: 8128.17 | E18: 9974.4 | F18: 9981.99 | G18: 10425.55 | H18: 17123.25 | I18: 18985.53 | J18: 17410.84 | K18: 17504.51
A19: Change in Inventory | B19: -199.33 | C19: 528.6 | D19: -142.13 | E19: 293.26 | F19: 239.15 | G19: 92.45 | H19: 1324.97 | I19: 309.73 | J19: -363.8 | K19: 205
A20: Power and Fuel | B20: 114.48 | C20: 106.02 | D20: 110.3 | E20: 119.63 | F20: 97.79 | G20: 86.05 | H20: 117.23 | I20: 138.29 | J20: 133.25 | K20: 148.58
A21: Other Mfr. Exp | B21: 1535.22 | C21: 1662.75 | D21: 1691.68 | E21: 1862.35 | F21: 1946.12 | G21: 2068.31 | H21: 2880.45 | I21: 2916.2 | J21: 2767.18 | K21: 2687.4
A22: Employee Cost | B22: 994.98 | C22: 1039.89 | D22: 1121.89 | E22: 1242.69 | F22: 1371.27 | G22: 1547.61 | H22: 1794.61 | I22: 2036.41 | J22: 2334.92 | K22: 2605.78
A23: Selling and admin | B23: 3912.3 | C23: 4364.04 | D23: 2254.92 | E23: 2366.87 | F23: 2311.51 | G23: 2245.69 | H23: 2941.98 | I23: 3500.84 | J23: 3811.86 | K23: 3874.94
A24: Other Expenses | B24: -1779.69 | C24: -2028.47 | D24: 171.45 | E24: 202.51 | F24: 579.95 | G24: 576.43 | H24: 765.12 | I24: 961.21 | J24: 1087.9 | K24: 1283.2
A25: Other Income | B25: 213.39 | C25: 337.9 | D25: 336.41 | E25: 273.77 | F25: 350.1 | G25: 331.65 | H25: 295.88 | I25: 431.46 | J25: 820.96 | K25: 350.22
A26: Depreciation | B26: 275.58 | C26: 334.79 | D26: 360.47 | E26: 622.14 | F26: 780.5 | G26: 791.27 | H26: 816.36 | I26: 858.02 | J26: 853 | K26: 1026.34
A27: Interest | B27: 49 | C27: 37.33 | D27: 41.47 | E27: 110.47 | F27: 102.33 | G27: 91.63 | H27: 95.41 | I27: 144.45 | J27: 205.17 | K27: 227.02
... A31: Dividend Amount | B31: 719.4 | C31: 987.98 | D31: 834.5 | E31: 1007.16 | F31: 1151.04 | G31: 1712.17 | H31: 1836.87 | I31: 2460.35 | J31: 3194.14 | K31: 2378.82
A32: Effective Tax Rate | B32: =B29/B28 -> 0.32308281 | C32: =C29/C28 -> 0.31872859 | D32: =D29/D28 -> 0.33167648 | E32: =E29/E28 -> 0.33213151 | F32: =F29/F28 -> 0.23555816 | G32: =G29/G28 -> 0.25499785 | H32: =H29/H28 -> 0.26336766 | I32: =I29/I28 -> 0.26253201 | ... K32: =K29/K28 -> 0.27304348
A34: EBITDA | B34: =+B30+B29+B27+B26 -> 2914.23 | C34: =+C30+C29+C27+C26 -> 3254.84 | D34: =+D30+D29+D27+D26 -> 3481.83 | E34: =+E30+E29+E27+E26 -> 3986.59 | F34: =+F30+F29+F27+F26 -> 4442.85 | G34: =+G30+G29+G27+G26 -> 5119.79 | H34: =+H30+H29+H27+H26 -> 5045.25 | I34: =+I30+I29+I27+I26 -> 6602.42 | ... K34: =+K30+K29+K27+K26 -> 6313.95
A40: Quarters
A41: Report Date | B41: 45199 | C41: 45291 | D41: 45382 | E41: 45473 | F41: 45565 | G41: 45657 | H41: 45747 | I41: 45838 | J41: 45930 | K41: 46022
A42: Sales | B42: 8478.57 | C42: 9103.09 | D42: 8730.76 | E42: 8969.73 | F42: 8027.54 | G42: 8549.44 | H42: 8358.91 | I42: 8938.55 | J42: 8531.27 | K42: 8867.02
A43: Expenses | B43: 6762.34 | C43: 7047 | D43: 7039.39 | E43: 7275.96 | F43: 6788.03 | G43: 6912.71 | H43: 6922.71 | I43: 7313.58 | J43: 7027.89 | K43: 7086.06
A44: Other Income | B44: 194.33 | C44: 186.46 | D44: 212.43 | E44: 192.93 | F44: 24.53 | G44: 192.82 | H44: -60.06 | I44: 229.11 | J44: 236.94 | K44: 69.14
A45: Depreciation | B45: 208.72 | C45: 220.35 | D45: 225.61 | E45: 227.7 | F45: 241.99 | G45: 255.55 | H45: 301.1 | I45: 300.87 | J45: 304.93 | K45: 313.07
A46: Interest | B46: 50.9 | C46: 54.42 | D46: 54.1 | E46: 55.38 | F46: 63.01 | G46: 55.84 | H46: 52.79 | I46: 44.5 | J46: 43.87 | K46: 47.94
A47: Profit before tax | B47: 1650.94 | C47: 1967.78 | D47: 1624.09 | E47: 1603.62 | F47: 959.04 | G47: 1518.16 | H47: 1022.25 | I47: 1508.71 | J47: 1391.52 | K47: 1489.09
A48: Tax | B48: 418.55 | C48: 492.62 | D48: 348.79 | E48: 416.83 | F48: 265.38 | G48: 389.73 | H48: 321.42 | I48: 391.66 | J48: 373.29 | K48: 415.17
A49: Net profit | B49: 1205.42 | C49: 1447.72 | D49: 1256.72 | E49: 1169.98 | F49: 694.64 | G49: 1110.48 | H49: 692.13 | I49: 1099.77 | J49: 993.59 | K49: 1059.87
A50: Operating Profit | B50: 1716.23 | C50: 2056.09 | D50: 1691.37 | E50: 1693.77 | F50: 1239.51 | G50: 1636.73 | H50: 1436.2 | I50: 1624.97 | J50: 1503.38 | K50: 1780.96
A51: EBITDA | B51: =B49+B48+B46+B45 -> 1883.59 | C51: =C49+C48+C46+C45 -> 2215.11 | D51: =D49+D48+D46+D45 -> 1885.22 | E51: =E49+E48+E46+E45 -> 1869.89 | F51: =F49+F48+F46+F45 -> 1265.02 | G51: =G49+G48+G46+G45 -> 1811.6 | H51: =H49+H48+H46+H45 -> 1367.44 | I51: =I49+I48+I46+I45 -> 1836.8 | ... K51: =K49+K48+K46+K45 -> 1836.05
A55: BALANCE SHEET
A56: Report Date | B56: 42460 | C56: 42825 | D56: 43190 | E56: 43555 | F56: 43921 | G56: 44286 | H56: 44651 | I56: 45016 | J56: 45382 | K56: 45747
A57: Equity Share Capital | B57: 95.92 | C57: 95.92 | D57: 95.92 | E57: 95.92 | F57: 95.92 | G57: 95.92 | H57: 95.92 | I57: 95.92 | J57: 95.92 | K57: 95.92
A58: Reserves | B58: 6428.9 | C58: 7507.97 | D58: 8314.31 | E58: 9374.63 | F58: 10034.24 | G58: 12710.37 | H58: 13715.64 | I58: 15896.31 | J58: 18632.38 | K58: 19303.89
A59: Borrowings | B59: 323.29 | C59: 560.34 | D59: 533.43 | E59: 1319.6 | F59: 1118.5 | G59: 1093.12 | H59: 1586.88 | I59: 1932.62 | J59: 2474.38 | K59: 2290.29
A60: Other Liabilities | B60: 3710.92 | C60: 4240.96 | D60: 4819.82 | E60: 5458.69 | F60: 4889.31 | G60: 6455.93 | H60: 7559.99 | I60: 7854.48 | J60: 8698.09 | K60: 8665.15
A61: Total | B61: 10559.03 | C61: 12405.19 | D61: 13763.48 | E61: 16248.84 | F61: 16137.97 | G61: 20355.34 | H61: 22958.43 | I61: 25779.33 | J61: 29900.77 | K61: 30355.25
A62: Net Block | B62: 3416.35 | C62: 3303.74 | D62: 3732.24 | E62: 6496.56 | F62: 6272.31 | G62: 5858.52 | H62: 5519.06 | I62: 5770.46 | J62: 7146.62 | K62: 9220.1
A63: Capital Work in Progress | B63: 106.59 | C63: 257.54 | D63: 1405.11 | E63: 209.67 | F63: 140.24 | G63: 182.98 | H63: 426.43 | I63: 1019.59 | J63: 2698.37 | K63: 1254.49
A64: Investments | B64: 2712.13 | C64: 2651.99 | D64: 2140.7 | E64: 2568.58 | F64: 2018.85 | G64: 4736.8 | H64: 3247.53 | I64: 4261.71 | J64: 4587.92 | K64: 4724.75
A65: Other Assets | B65: 4323.96 | C65: 6191.92 | D65: 6485.43 | E65: 6974.03 | F65: 7706.57 | G65: 9577.04 | H65: 13765.41 | I65: 14727.57 | J65: 15467.86 | K65: 15155.91
A66: Total | B66: 10559.03 | C66: 12405.19 | D66: 13763.48 | E66: 16248.84 | F66: 16137.97 | G66: 20355.34 | H66: 22958.43 | I66: 25779.33 | J66: 29900.77 | K66: 30355.25
A67: Receivables | B67: 1186.84 | C67: 1446.6 | D67: 1730.63 | E67: 1907.33 | F67: 1795.22 | G67: 2602.17 | H67: 3871.44 | I67: 4636.94 | J67: 4889.05 | K67: 4313.65
... A70: No. of Equity Shares | B70: 959197790 | C70: 959197790 | D70: 959197790 | E70: 959197790 | F70: 959197790 | G70: 959197790 | H70: 959197790 | I70: 959197790 | J70: 959197790 | K70: 959197790
A71: New Bonus Shares
A72: Face value | B72: 1 | C72: 1 | D72: 1 | E72: 1 | F72: 1 | G72: 1 | H72: 1 | I72: 1 | J72: 1 | K72: 1
H73: =H62-G62+H45 -> -38.36 | I73: =I62-H62+I45 -> 552.27 | J73: =J62-I62+J45 -> 1681.09 | K73: =K62-J62+K45 -> 2386.55
A80: CASH FLOW:
A81: Report Date | B81: 42460 | C81: 42825 | D81: 43190 | E81: 43555 | F81: 43921 | G81: 44286 | H81: 44651 | I81: 45016 | J81: 45382 | K81: 45747
A82: Cash from Operating Activity | B82: 2242.95 | C82: 1527.33 | D82: 2113.44 | E82: 2469.54 | F82: 3038.15 | G82: 3683.35 | H82: 986.49 | I82: 4193.43 | J82: 6103.6 | K82: 4423.96
A83: Cash from Investing Activity | B83: -866.21 | C83: -681.11 | D83: -1556.14 | E83: -917.79 | F83: -517.91 | G83: -540.54 | H83: -316.75 | I83: -1282.34 | J83: -2548.48 | K83: -940.91
A84: Cash from Financing Activity | B84: -848.98 | C84: -756.43 | D84: -1379.14 | E84: -1117.46 | F84: -2871.46 | G84: -650.4 | H84: -1807.61 | I84: -2140.05 | J84: -2982.5 | K84: -3752.58
A85: Net Cash Flow | B85: 527.76 | C85: 89.79 | D85: -821.84 | E85: 434.29 | F85: -351.22 | G85: 2492.41 | H85: -1137.87 | I85: 771.04 | J85: 572.62 | K85: -269.53
A90: PRICE: | B90: 868.4 | C90: 1073.5 | D90: 1120.4 | E90: 1492.7 | F90: 1666.5 | G90: 2537.4 | H90: 3079.95 | I90: 2761.65 | J90: 2846.75 | K90: 2340.65
A92: DERIVED:
A93: Adjusted Equity Shares in Cr | B93: 95.92 | C93: 95.92 | D93: 95.92 | E93: 95.92 | F93: 95.92 | G93: 95.92 | H93: 95.92 | I93: 95.92 | J93: 95.92 | K93: 95.92

Sheet Data Sheet 2
E1: make changes according to the Column TO THIS SHEET
C2: 41699 | D2: 42064 | E2: 42430 | F2: 42795 | G2: 43160 | H2: 43525 | I2: 43891 | J2: 44256 | K2: 44621 | L2: 44986 | M2: 45352 | N2: 45717 | O2: 45901
B3: Equity Capital | C3: 96 | D3: 96 | E3: 96 | F3: 96 | G3: 96 | H3: 96 | I3: 96 | J3: 96 | K3: 96 | L3: 96 | M3: 96 | N3: 96 | O3: 96
B4: Reserves | C4: 3943 | D4: 4646 | E4: 6429 | F4: 7508 | G4: 8314 | H4: 9375 | I4: 10034 | J4: 12710 | K4: 13716 | L4: 15896 | M4: 18632 | N4: 19304 | O4: 19483
B5: Borrowings - | C5: 249 | D5: 418 | E5: 323 | F5: 560 | G5: 533 | H5: 1320 | I5: 1118 | J5: 1093 | K5: 1587 | L5: 1933 | M5: 2474 | N5: 2290 | O5: 3557
B6: Long term Borrowings | C6: 41 | D6: 78 | E6: 73 | F6: 41 | G6: 28 | H6: 19 | I6: 19 | J6: 15 | K6: 45 | L6: 76 | M6: 54 | N6: 260 | O6: 911
B7: Short term Borrowings | C7: 199 | D7: 332 | E7: 231 | F7: 504 | G7: 492 | H7: 597 | I7: 321 | J7: 334 | K7: 731 | L7: 896 | M7: 1053 | N7: 604 | O7: 1047
B8: Lease Liabilities | C8: 0 | D8: 0 | E8: 0 | F8: 0 | G8: 0 | H8: 693 | I8: 764 | J8: 745 | K8: 811 | L8: 960 | M8: 1367 | N8: 1427 | O8: 1600
B9: Other Borrowings | C9: 9 | D9: 8 | E9: 20 | F9: 15 | G9: 13 | H9: 11 | I9: 15 | J9: 0 | K9: 0 | L9: 0 | M9: 0 | N9: 0
B10: Other Liabilities - | C10: 3787 | D10: 3754 | E10: 3711 | F10: 4241 | G10: 4820 | H10: 5459 | I10: 4889 | J10: 6456 | K10: 7560 | L10: 7854 | M10: 8698 | N10: 8665 | O10: 8213
B11: Non controlling int | C11: 246 | D11: 264 | E11: 384 | F11: 375 | G11: 328 | H11: 361 | I11: 404 | J11: 423 | K11: 388 | L11: 454 | M11: 695 | N11: 659 | O11: 622
B12: Trade Payables | C12: 1746 | D12: 1549 | E12: 1565 | F12: 1923 | G12: 2160 | H12: 2394 | I12: 2137 | J12: 3379 | K12: 4164 | L12: 3635 | M12: 3831 | N12: 3848 | O12: 3375
B13: Advance from Customers | C13: 0 | D13: 5 | E13: 12 | F13: 17 | G13: 16 | H13: 13 | I13: 29 | J13: 41 | K13: 76 | L13: 108 | M13: 154 | N13: 173
B14: Other liability items | C14: 1795 | D14: 1937 | E14: 1750 | F14: 1925 | G14: 2316 | H14: 2690 | I14: 2320 | J14: 2613 | K14: 2932 | L14: 3657 | M14: 4017 | N14: 3985 | O14: 4216
B15: Total Liabilities | C15: 8075 | D15: 8914 | E15: 10559 | F15: 12405 | G15: 13763 | H15: 16249 | I15: 16138 | J15: 20355 | K15: 22958 | L15: 25779 | M15: 29901 | N15: 30355 | O15: 31349
B16: Fixed Assets - | C16: 2562 | D16: 2660 | E16: 3416 | F16: 3304 | G16: 3732 | H16: 6497 | I16: 6272 | J16: 5859 | K16: 5519 | L16: 5770 | M16: 7147 | N16: 9220 | O16: 9219
B17: Land | C17: 247 | D17: 251 | E17: 429 | F17: 408 | G17: 586 | H17: 605 | I17: 640 | J17: 644 | K17: 644 | L17: 804 | M17: 1126 | N17: 1050
B18: Building | C18: 931 | D18: 962 | E18: 923 | F18: 931 | G18: 957 | H18: 2402 | I18: 2257 | J18: 2249 | K18: 2325 | L18: 2883 | M18: 3390 | N18: 4136
B19: Plant Machinery | C19: 2054 | D19: 2132 | E19: 1793 | F19: 1980 | G19: 2157 | H19: 4006 | I19: 4208 | J19: 4340 | K19: 4531 | L19: 4825 | M19: 5422 | N19: 7576
B20: Equipments | C20: 155 | D20: 171 | E20: 97 | F20: 119 | G20: 200 | H20: 221 | I20: 241 | J20: 243 | K20: 253 | L20: 270 | M20: 298 | N20: 325
B21: Furniture n fittings | C21: 71 | D21: 83 | E21: 49 | F21: 59 | G21: 72 | H21: 88 | I21: 94 | J21: 99 | K21: 113 | L21: 146 | M21: 175 | N21: 203
B22: Vehicles | C22: 14 | D22: 18 | E22: 11 | F22: 14 | G22: 27 | H22: 47 | I22: 43 | J22: 38 | K22: 32 | L22: 36 | M22: 40 | N22: 39
B23: Intangible Assets | C23: 203 | D23: 351 | E23: 339 | F23: 276 | G23: 468 | H23: 512 | I23: 505 | J23: 476 | K23: 345 | L23: 422 | M23: 850 | N23: 827 | O23: 574
B24: Other fixed assets | C24: 128 | D24: 145 | E24: 103 | F24: 128 | G24: 238 | H24: 261 | I24: 293 | J24: 302 | K24: 294 | L24: 289 | M24: 321 | N24: 328
B25: Gross Block | C25: 3804 | D25: 4112 | E25: 3744 | F25: 3914 | G25: 4705 | H25: 8141 | I25: 8282 | J25: 8392 | K25: 8538 | L25: 9676 | M25: 11622 | N25: 14484
B26: Accumulated Depreciation | C26: 1242 | D26: 1452 | E26: 327 | F26: 610 | G26: 973 | H26: 1644 | I26: 2010 | J26: 2533 | K26: 3019 | L26: 3905 | M26: 4475 | N26: 5264
B27: CWIP | C27: 72 | D27: 196 | E27: 107 | F27: 258 | G27: 1405 | H27: 210 | I27: 140 | J27: 183 | K27: 426 | L27: 1020 | M27: 2698 | N27: 1254 | O27: 1766
B28: Investments | C28: 1424 | D28: 1588 | E28: 2712 | F28: 2652 | G28: 2141 | H28: 2569 | I28: 2019 | J28: 4737 | K28: 3248 | L28: 4262 | M28: 4588 | N28: 4725 | O28: 5431
B29: Other Assets - | C29: 4019 | D29: 4471 | E29: 4324 | F29: 6192 | G29: 6485 | H29: 6974 | I29: 7707 | J29: 9577 | K29: 13765 | L29: 14728 | M29: 15468 | N29: 15156 | O29: 14932
B30: Inventories | C30: 2070 | D30: 2259 | E30: 1998 | F30: 2627 | G30: 2658 | H30: 3150 | I30: 3390 | J30: 3799 | K30: 6153 | L30: 6211 | M30: 5923 | N30: 6719 | O30: 6011
B31: Trade receivables + | C31: 1110 | D31: 1182 | E31: 1187 | F31: 1447 | G31: 1731 | H31: 1907 | I31: 1795 | J31: 2602 | K31: 3871 | L31: 4637 | M31: 4889 | N31: 4314 | O31: 4424
B32: Cash Equivalents | C32: 229 | D32: 204 | E32: 424 | F32: 801 | G32: 405 | H32: 445 | I32: 783 | J32: 611 | K32: 864 | L32: 844 | M32: 1084 | N32: 782 | O32: 1011
B33: Loans n Advances | C33: 7 | D33: 8 | E33: 9 | F33: 14 | G33: 13 | H33: 16 | I33: 12 | J33: 11 | K33: 8 | L33: 12 | M33: 17 | N33: 22 | O33: 1066
B34: Other asset items | C34: 603 | D34: 817 | E34: 705 | F34: 1303 | G34: 1678 | H34: 1456 | I34: 1727 | J34: 2555 | K34: 2869 | L34: 3024 | M34: 3555 | N34: 3319 | O34: 2421
B35: Total Assets | C35: 8075 | D35: 8914 | E35: 10559 | F35: 12405 | G35: 13763 | H35: 16249 | I35: 16138 | J35: 20355 | K35: 22958 | L35: 25779 | M35: 29901 | N35: 30355 | O35: 31349

Sheet Relative Data
E1: MC/CMP | H1: MC+DBT-EV | L1: ev/ev/ebitda | M1: market cap/pe
B2: S.No. | C2: Name | D2: CMP Rs. | E2: no of equity share | F2: Mar Cap Rs.Cr. | G2: Debt Rs.Cr. | H2: Cash | I2: Net Debt | J2: EV Rs.Cr. | K2: Sales Rs.Cr. | L2: EBITDA | M2: NP | O2: P/E | P2: Debt / Eq | Q2: OPM % | R2: EV / EBITDA | S2: Ind PE
B3: 1 | C3: Asian Paints | D3: ='Data Sheet'!B8 -> 2605.6 | E3: ='Data Sheet'!B6 -> 95.91978 | F3: ='Data Sheet'!B9 -> 249928.58 | G3: =SUM('Raw FS'!N7:N9) -> 2291 | H3: ='Data Sheet'!K69 -> 781.98 | I3: =G3-H3 -> 1509.02 | J3: =F3+I3 -> 251437.6 | K3: =HistoricalFS!L6 -> 33905.62 | L3: ='Data Sheet'!K34 -> 6313.95 | M3: ='Data Sheet'!K30 -> 3667.23 | O3: =F3/M3 -> 68.151869 | P3: ='Beta - Comps'!G4 -> 0.0091666187 | Q3: =(('Data Sheet'!K34-'Data Sheet'!K26)/'Data Sheet'!K17)*100 -> 15.595084 | R3: =J3/L3 -> 39.822552 | S3: 38.25
B4: 2 | C4: Berger Paints | D4: 545.75 | E4: =F4/D4 -> 116.60027 | F4: 63634.6 | G4: 635.13 | H4: =F4+G4-J4 -> 305.31 | I4: =G4-H4 -> 329.82 | J4: 63964.42 | K4: 11880.25 | L4: =J4/R4 -> 1990.8005 | M4: =F4/O4 -> 1165.8959 | O4: 54.58 | P4: 0.09 | Q4: 15.43 | R4: 32.13 | S4: 38.25
B5: 3 | C5: Kansai Nerolac | D5: 216 | E5: =F5/D5 -> 80.871435 | F5: 17468.23 | G5: 302.73 | H5: =F5+G5-J5 -> 225.78 | I5: =G5-H5 -> 76.95 | J5: 17545.18 | K5: 8051.91 | L5: =J5/R5 -> 1049.3529 | M5: =F5/O5 -> 579.18534 | O5: 30.16 | P5: 0.05 | Q5: 12.1 | R5: 16.72 | S5: 38.25
B6: 4 | C6: JSW Dulux | D6: 3205.35 | E6: =F6/D6 -> 4.5540331 | F6: 14597.27 | G6: 79.1 | H6: =F6+G6-J6 -> 323.7 | I6: =G6-H6 -> -244.6 | J6: 14352.67 | K6: 3599.2 | L6: =J6/R6 -> 521.15723 | M6: =F6/O6 -> 361.13978 | O6: 40.42 | P6: 0.03 | Q6: 14.15 | R6: 27.54 | S6: 38.25
B7: 5 | C7: Indigo Paints | D7: 1060.5 | E7: =F7/D7 -> 4.7675719 | F7: 5056.01 | G7: 18.37 | H7: =F7+G7-J7 -> 28.55 | I7: =G7-H7 -> -10.18 | J7: 5045.83 | K7: 1330.12 | L7: =J7/R7 -> 258.89328 | M7: =F7/O7 -> 149.67466 | O7: 33.78 | P7: 0.02 | Q7: 18.55 | R7: 19.49 | S7: 38.25
B8: 6 | C8: Sirca Paints | D8: 419.7 | E8: =F8/D8 -> 5.6792709 | F8: 2383.59 | G8: 32.32 | H8: =F8+G8-J8 -> 57.98 | I8: =G8-H8 -> -25.66 | J8: 2357.93 | K8: 492.48 | L8: =J8/R8 -> 102.74205 | M8: =F8/O8 -> 65.018822 | O8: 36.66 | P8: 0.07 | Q8: 20.08 | R8: 22.95 | S8: 38.25

Sheet List Of Stocks
B2: COMPANY_NAME | C2: BSE | D2: NSE | E2: Industry
B3: 20 MICRONS LTD | C3: 533022 | D3: 20MICRONS | E3: Mining
B4: 21ST CENTURY MANAGEMENT SERVICES LTD | C4: 526921 | D4: 21STCENMGM | E4: Other Financial Services
B5: 3I INFOTECH LTD | C5: 532628 | D5: 3IINFOTECH | E5: IT Consulting & Software
B6: 3M (INDIA) LTD | C6: 523395 | D6: 3M(INDIA) | E6: Diversified
B7: 3M INDIA LTD | C7: 523395 | D7: 3MINDIA | E7: Diversified
B8: 3P LAND HOLDINGS LTD | C8: 516092 | D8: 3PLAND | E8: Paper & Paper Products
B9: 5PAISA CAPITAL LTD | C9: 540776 | D9: 5PAISA | E9: Other Financial Services
B10: 63 MOONS TECHNOLOGIES LTD | C10: 526881 | D10: 63MOONS | E10: IT Consulting & Software
B11: 7NR RETAIL LTD | C11: 540615 | D11: Not Listed | E11: Specialty Retail
B12: 7SEAS ENTERTAINMENT LTD | C12: 540874 | D12: Not Listed | E12: Movies & Entertainment
B13: 8K MILES SOFTWARE SERVICES LTD | C13: 512161 | D13: 8KMILES | E13: Internet Software & Services
B14: A & M FEBCON LTD | C14: 540697 | D14: Not Listed | E14: Industrial Machinery
B15: A AND M JUMBO BAGS LTD | C15: Not Listed | D15: AMJUMBO | E15: SME
B16: A INFRASTRUCTURE LTD | C16: 539620 | D16: Not Listed | E16: Cement & Cement Products
B17: A K SPINTEX LTD | C17: 539300 | D17: Not Listed | E17: Textiles
B18: A K CAPITAL SERVICES LTD | C18: 530499 | D18: Not Listed | E18: Finance (including NBFCs)
B19: A.F. Enterprises Ltd | C19: 538351 | D19: AFEL | E19: Investment Companies
B20: A-1 ACID LTD | C20: 542012 | D20: Not Listed | E20: Comm.Trading & Distribution
B21: A2Z INFRA ENGINEERING LTD | C21: 533292 | D21: A2ZINFRA | E21: Utilities:Non-Elec.
B22: AADHAAR VENTURES (INDIA) LTD | C22: 531611 | D22: Not Listed | E22: Finance (including NBFCs)
B23: AADHAAR VENTURES INDIA LTD | C23: 531611 | D23: Not Listed | E23: Finance (including NBFCs)
B24: AAKASH EXPLORATION SERVICES LTD | C24: Not Listed | D24: AAKASH | E24: SME
B25: AANANDA LAKSHMI SPINNING MILLS LTD | C25: 539096 | D25: Not Listed | E25: Textiles
B26: AANCHAL ISPAT LTD | C26: 538812 | D26: Not Listed | E26: Iron & Steel/Interm.Products
B27: AAR COMMERCIAL COMPANY LTD | C27: 539632 | D27: Not Listed | E27: Distributors
B28: Aar Shyam India Investment Company Ltd | C28: 542377 | D28: AARSHYAM | E28: Finance (including NBFCs)
B29: AAREY DRUGS & PHARMACEUTICALS LTD | C29: 524412 | D29: Not Listed | E29: Pharmaceuticals
B30: AARON INDUSTRIES LTD | C30: Not Listed | D30: AARON | E30: SME
B31: Aartech Solonics Ltd | C31: 542580 | D31: AARTECH | E31: Heavy Electrical Equipment
B32: AARTI DRUGS LTD | C32: 524348 | D32: AARTIDRUGS | E32: Pharmaceuticals
B33: AARTI INDUSTRIES LTD | C33: 524208 | D33: AARTIIND | E33: Commodity Chemicals
B34: AARV INFRATEL LTD | C34: 526488 | D34: Not Listed | E34: Textiles
B35: AARVEE DENIMS & EXPORTS LTD | C35: 514274 | D35: AARVEEDEN | E35: Textiles
B36: AARVI ENCON LTD | C36: Not Listed | D36: AARVI | E36: SME
B37: AASHEE INFOTECH LTD | C37: 519319 | D37: Not Listed | E37: Internet Software & Services
B38: AASWA TRADING & EXPORTS LTD | C38: 512038 | D38: Not Listed | E38: Comm.Trading & Distribution
B39: AAVAS FINANCIERS LTD | C39: 541988 | D39: AAVAS | E39: Housing Finance
B40: AAYUSH FOOD AND HERBS LTD | C40: 539528 | D40: Not Listed | E40: Packaged Foods
B41: ABAN OFFSHORE LTD | C41: 523204 | D41: ABAN | E41: Exploration & Production
B42: ABANS ENTERPRISES LTD | C42: 512165 | D42: Not Listed | E42: Comm.Trading & Distribution
B43: ABB INDIA LTD | C43: 500002 | D43: ABB | E43: Heavy Electrical Equipment
B44: ABBOTT (INDIA) LTD | C44: 500488 | D44: ABBOT(INDIA) | E44: Pharmaceuticals
B45: ABBOTT INDIA LTD | C45: 500488 | D45: ABBOTINDIA | E45: Pharmaceuticals
B46: ABC (INDIA) LTD | C46: 520123 | D46: Not Listed | E46: Surface Transportation
B47: ABC GAS INTERNATIONAL LTD | C47: 513119 | D47: Not Listed | E47: Copper
B48: ABC INDIA LTD | C48: 520123 | D48: Not Listed | E48: Surface Transportation
... B56: ABIRAMI FINANCIAL SERVICES INDIA LTD | C56: 511756 | D56: Not Listed | E56: Finance (including NBFCs)
B57: ABM INTERNATIONAL LTD | C57: Not Listed | D57: ABMINTLTD | E57: Others
B58: ABM KNOWLEDGEWARE LTD | C58: 531161 | D58: Not Listed | E58: IT Software Products
B59: ACC LTD | C59: 500410 | D59: ACC | E59: Cement & Cement Products
B60: ACCEL LTD | C60: 517494 | D60: Not Listed | E60: Storage Media & Peripherals
B61: ACCELYA KALE SOLUTIONS LTD | C61: 532268 | D61: ACCELYA | E61: IT Consulting & Software
B62: ACCORD SYNERGY LTD | C62: Not Listed | D62: ACCORD | E62: SME
B63: ACCURACY SHIPPING LTD | C63: Not Listed | D63: ACCURACY | E63: SME
B64: ACE EDUTREND LTD | C64: 530093 | D64: Not Listed | E64: Education
B65: ACE INTEGRATED SOLUTIONS LTD | C65: Not Listed | D65: ACEINTEG | E65: SME
B66: ACE MEN ENGG WORKS LTD | C66: 539661 | D66: Not Listed | E66: Distributors
B67: ACE SOFTWARE EXPORTS LTD | C67: 531525 | D67: Not Listed | E67: IT Software Products
B68: Achal Investments Ltd | C68: 538570 | D68: ACHAL | E68: Other Financial Services
B69: ACI INFOCOM LTD | C69: 517356 | D69: Not Listed | E69: Storage Media & Peripherals
B70: ACKNIT INDUSTRIES LTD | C70: 530043 | D70: Not Listed | E70: Other Apparels & Accessories
B71: ACME RESOURCES LTD | C71: 539391 | D71: Not Listed | E71: Finance (including NBFCs)
B72: ACROW INDIA LTD. | C72: 513149 | D72: ACROW | E72: Iron &amp; Steel Products
B73: ACRYSIL LTD | C73: 524091 | D73: Not Listed | E73: Plastic Products
B74: ACTION CONSTRUCTION EQUIPMENT LTD | C74: 532762 | D74: ACE | E74: Transport Related Services
B75: ACTION FINANCIAL SERVICES (INDIA) LTD | C75: 511706 | D75: Not Listed | E75: Other Financial Services
B76: ACTION FINANCIAL SERVICES INDIA LTD | C76: 511706 | D76: Not Listed | E76: Other Financial Services
B77: ACTIVE CLOTHING CO LTD | C77: 541144 | D77: Not Listed | E77: Other Apparels & Accessories
... B135: AGRI-TECH INDIA LTD | C135: 537292 | D135: AGRITECH | E135: Other Agricultural Products
B136: AGRO PHOS (INDIA) LTD | C136: Not Listed | D136: AGROPHOS | E136: SME
B137: AGRO PHOS INDIA LTD | C137: Not Listed | D137: AGROPHOS | E137: SME
B138: AGRO TECH FOODS LTD | C138: 500215 | D138: ATFL | E138: Other Agricultural Products
B139: AHIMSA INDUSTRIES LTD | C139: Not Listed | D139: AHIMSA | E139: SME
B140: AHLADA ENGINEERS LTD | C140: Not Listed | D140: AHLADA | E140: SME
B141: AHLUWALIA CONTRACTS (INDIA) LTD | C141: 532811 | D141: AHLUCONT | E141: Realty
B142: AHLUWALIA CONTRACTS INDIA LTD | C142: 532811 | D142: AHLUCONT | E142: Realty
B143: AHMEDABAD STEELCRAFT LTD | C143: 522273 | D143: Not Listed | E143: Iron & Steel/Interm.Products
B144: AI CHAMPDANY INDUSTRIES LTD | C144: 532806 | D144: Not Listed | E144: Jute & Jute Products
B145: AIA ENGINEERING LTD | C145: 532683 | D145: AIAENG | E145: Other Industrial Goods
B146: AIMCO PESTICIDES LTD | C146: 524288 | D146: Not Listed | E146: Agrochemicals
B147: AIRAN LTD | C147: Not Listed | D147: AIRAN | E147: SME
B148: AIRO LAM LTD | C148: Not Listed | D148: AIROLAM | E148: SME
B149: AISHWARYA TELECOM LTD | C149: 532975 | D149: Not Listed | E149: Telecom Equipment
B150: AJANTA PHARMA LTD | C150: 532331 | D150: AJANTPHARM | E150: Pharmaceuticals
B151: AJANTA SOYA LTD | C151: 519216 | D151: Not Listed | E151: Edible Oils
B152: AJCON GLOBAL SERVICES LTD | C152: 511692 | D152: Not Listed | E152: Other Financial Services
B153: AJEL LTD | C153: 530713 | D153: Not Listed | E153: IT Consulting & Software
B154: AJMERA REALTY & INFRA (INDIA) LTD | C154: 513349 | D154: AJMERA | E154: Realty
B155: AJMERA REALTY & INFRA INDIA LTD | C155: 513349 | D155: AJMERA | E155: Realty
B156: AJOONI BIOTECH LTD | C156: Not Listed | D156: AJOONI | E156: SME
B157: AJWA FUN WORLD & RESORT LTD | C157: 526628 | D157: Not Listed | E157: Other Leisure Facilities
B158: AKAR AUTO INDUSTRIES LTD | C158: 530621 | D158: Not Listed | E158: Industrial Machinery
B159: AKASH INFRA PROJECTS LTD | C159: Not Listed | D159: AKASH | E159: SME
B160: AKASHDEEP METAL INDUSTRIES LTD | C160: 538778 | D160: Not Listed | E160: Finance (including NBFCs)
B161: AKG EXIM LTD | C161: Not Listed | D161: AKG | E161: SME
B162: AKI (INDIA) LTD | C162: 542020 | D162: Not Listed | E162: Other Apparels & Accessories
B163: AKI INDIA LTD | C163: 542020 | D163: Not Listed | E163: Other Apparels & Accessories
B164: AKM LACE AND EMBROTEX LTD | C164: 540718 | D164: Not Listed | E164: Textiles
B165: AKME STAR HOUSING FINANCE LTD | C165: 539017 | D165: Not Listed | E165: Housing Finance
...
